DAY2/Assignment 2/3_bit_binary_to_gray.v
/*
 * 4-bit binary-to-Gray code converter
 * Dataflow model using continuous assignments.
 */

module binary_to_gray (
	input  [3:0] binary,
	output [3:0] gray
);

	assign gray[3] = binary[3];
	assign gray[2] = binary[3] ^ binary[2];
	assign gray[1] = binary[2] ^ binary[1];
	assign gray[0] = binary[1] ^ binary[0];

endmodule

DAY2/Assignment 2/3_bit_binary_to_gray_tb.v
/*
 * Testbench for the 4-bit binary-to-Gray code converter.
 * Exhaustively tests all binary values from 0 to 15.
 */

`timescale 1ns/1ps

module binary_to_gray_tb;

    reg  [3:0] binary;
    wire [3:0] gray;

    integer binary_value;
    integer expected_gray;
    integer test_count;
    integer failure_count;

    binary_to_gray dut (
        .binary(binary),
        .gray(gray)
    );

    initial begin
        $dumpfile("3_bit_binary_to_gray_tb.vcd");
        $dumpvars(0, binary_to_gray_tb);

        test_count = 0;
        failure_count = 0;

        $display("===============================================");
        $display("      4-bit Binary-to-Gray Converter Test      ");
        $display("===============================================");
        $display("Formula: Gray = Binary ^ (Binary >> 1)");
        $display("Testing all 16 binary input combinations...\n");
        $display("Time\tTest\tBinary(dec)\tBinary\tGray\tGray(dec)\tExpected");

        for (binary_value = 0; binary_value < 16; binary_value = binary_value + 1) begin
            binary = binary_value;
            #1;

            expected_gray = (binary_value >> 1) ^ binary_value;
            test_count = test_count + 1;

            $display("%0t\t%0d\t%0d\t\t%b\t%b\t%0d\t\t%b",
                     $time, test_count, binary_value, binary, gray,
                     gray, expected_gray[3:0]);

            if (gray !== expected_gray[3:0]) begin
                $display("  FAIL: Binary=%0d (%b), Expected Gray=%0d (%b), Got Gray=%0d (%b)",
                         binary_value, binary, expected_gray, expected_gray[3:0], gray, gray);
                failure_count = failure_count + 1;
            end
        end

        if (failure_count == 0) begin
            $display("\nPASS: %0d/%0d binary-to-Gray tests completed successfully.",
                     test_count, test_count);
            $display("All Gray-code outputs match the expected values.");
        end else begin
            $display("\nFAIL: %0d of %0d binary-to-Gray tests failed.",
                     failure_count, test_count);
            $fatal(1);
        end

        $finish;
    end

endmodule

DAY2/Assignment 2/3_bit_binary_to_gray_tb.vcd
$date
	Wed Sep 23 05:16:28 2026
$end
$version
	Icarus Verilog
$end
$timescale
	1ps
$end
$scope module binary_to_gray_tb $end
$var wire 4 ! gray [3:0] $end
$var reg 4 " binary [3:0] $end
$var integer 32 # binary_value [31:0] $end
$var integer 32 $ expected_gray [31:0] $end
$var integer 32 % failure_count [31:0] $end
$var integer 32 & test_count [31:0] $end
$scope module dut $end
$var wire 4 ' binary [3:0] $end
$var wire 4 ( gray [3:0] $end
$upscope $end
$upscope $end
$enddefinitions $end
$comment Show the parameter values. $end
$dumpall
$end
#0
$dumpvars
b0 (
b0 '
b0 &
b0 %
bx $
b0 #
b0 "
b0 !
$end
#1000
b1 !
b1 (
b1 "
b1 '
b1 #
b1 &
b0 $
#2000
b11 !
b11 (
b10 "
b10 '
b10 #
b10 &
b1 $
#3000
b10 !
b10 (
b11 "
b11 '
b11 #
b11 &
b11 $
#4000
b110 !
b110 (
b100 "
b100 '
b100 #
b100 &
b10 $
#5000
b111 !
b111 (
b101 "
b101 '
b101 #
b101 &
b110 $
#6000
b101 !
b101 (
b110 "
b110 '
b110 #
b110 &
b111 $
#7000
b100 !
b100 (
b111 "
b111 '
b111 #
b111 &
b101 $
#8000
b1100 !
b1100 (
b1000 "
b1000 '
b1000 #
b1000 &
b100 $
#9000
b1101 !
b1101 (
b1001 "
b1001 '
b1001 #
b1001 &
b1100 $
#10000
b1111 !
b1111 (
b1010 "
b1010 '
b1010 #
b1010 &
b1101 $
#11000
b1110 !
b1110 (
b1011 "
b1011 '
b1011 #
b1011 &
b1111 $
#12000
b1010 !
b1010 (
b1100 "
b1100 '
b1100 #
b1100 &
b1110 $
#13000
b1011 !
b1011 (
b1101 "
b1101 '
b1101 #
b1101 &
b1010 $
#14000
b1001 !
b1001 (
b1110 "
b1110 '
b1110 #
b1110 &
b1011 $
#15000
b1000 !
b1000 (
b1111 "
b1111 '
b1111 #
b1111 &
b1001 $
#16000
b10000 #
b10000 &
b1000 $
