DAY2/Assignment 3/bcd_to_seven_segment_dataflow.v
/*
 * 4-bit BCD-to-seven-segment display decoder.
 * Combinational case decoder.
 *
 * Seven-segment display:
 *       ---
 *      |   |
 *      |   |
 *       ---
 *      |   |
 *      |   |
 *       ---
 *
 * Segment numbering:
 *       --- 0 ---
 *      |         |
 *    5 |         | 1
 *      |--- 6 ---|
 *      |         |
 *    4 |         | 2
 *      |--- 3 ---|
 *
 * A segment value of 1 turns that segment on.
 * Output order: {segment[6], segment[5], ..., segment[0]}.
 *
 * BCD     Digit     segment[6:0]
 * 0000      0          0111111
 * 0001      1          0000110
 * 0010      2          1011011
 * 0011      3          1001111
 * 0100      4          1100110
 * 0101      5          1101101
 * 0110      6          1111101
 * 0111      7          0000111
 * 1000      8          1111111
 * 1001      9          1101111
 *
 * Invalid BCD inputs (1010 to 1111) turn all segments off.
 */

module bcd_to_seven_segment_dataflow (
    input  [3:0] bcd,
    output reg [6:0] segment
);

    always @(*) begin
        case (bcd)
            4'd0:    segment = 7'b0111111;
            4'd1:    segment = 7'b0000110;
            4'd2:    segment = 7'b1011011;
            4'd3:    segment = 7'b1001111;
            4'd4:    segment = 7'b1100110;
            4'd5:    segment = 7'b1101101;
            4'd6:    segment = 7'b1111101;
            4'd7:    segment = 7'b0000111;
            4'd8:    segment = 7'b1111111;
            4'd9:    segment = 7'b1101111;
            default: segment = 7'b0000000;
        endcase
    end

endmodule

DAY2/Assignment 3/bcd_to_seven_segment_dataflow_tb.v
/*
 * Testbench for the 4-bit BCD-to-seven-segment display decoder.
 * Tests all valid BCD digits from 0 to 9.
 */

`timescale 1ns/1ps

module bcd_to_seven_segment_dataflow_tb;

    reg  [3:0] bcd;
    wire [6:0] segment;
    reg  [6:0] expected_segment;

    integer bcd_value;
    integer test_count;
    integer failure_count;

    bcd_to_seven_segment_dataflow dut (
        .bcd(bcd),
        .segment(segment)
    );

    function [6:0] expected_segments;
        input [3:0] digit;
        begin
            case (digit)
                4'd0: expected_segments = 7'b0111111;
                4'd1: expected_segments = 7'b0000110;
                4'd2: expected_segments = 7'b1011011;
                4'd3: expected_segments = 7'b1001111;
                4'd4: expected_segments = 7'b1100110;
                4'd5: expected_segments = 7'b1101101;
                4'd6: expected_segments = 7'b1111101;
                4'd7: expected_segments = 7'b0000111;
                4'd8: expected_segments = 7'b1111111;
                4'd9: expected_segments = 7'b1101111;
                default: expected_segments = 7'b0000000;
            endcase
        end
    endfunction

    initial begin
        $dumpfile("bcd_to_seven_segment_dataflow_tb.vcd");
        $dumpvars(0, bcd_to_seven_segment_dataflow_tb);

        test_count = 0;
        failure_count = 0;

        $display("=======================================================");
        $display("          BCD-to-Seven-Segment Decoder Test           ");
        $display("=======================================================");
        $display("Segment order: {6, 5, 4, 3, 2, 1, 0}; 1 = ON");
        $display("Time\tTest\tBCD\tSegments\tExpected");

        for (bcd_value = 0; bcd_value < 10; bcd_value = bcd_value + 1) begin
            bcd = bcd_value;
            #1;

            expected_segment = expected_segments(bcd);
            test_count = test_count + 1;

            $display("%0t\t%0d\t%0d\t%b\t%b", $time, test_count,
                     bcd_value, segment, expected_segment);

            if (segment !== expected_segment) begin
                $display("  FAIL: BCD=%0d, Expected=%b, Got=%b",
                         bcd_value, expected_segment, segment);
                failure_count = failure_count + 1;
            end
        end

        if (failure_count == 0) begin
            $display("\nPASS: %0d/%0d BCD-to-seven-segment tests completed successfully.",
                     test_count, test_count);
        end else begin
            $display("\nFAIL: %0d of %0d tests failed.", failure_count, test_count);
            $fatal(1);
        end

        $finish;
    end

endmodule

DAY2/Assignment 3/bcd_to_seven_segment_dataflow_tb.vcd
$date
	Wed Sep 23 05:54:54 2026
$end
$version
	Icarus Verilog
$end
$timescale
	1ps
$end
$scope module bcd_to_seven_segment_dataflow_tb $end
$var wire 7 ! segment [6:0] $end
$var reg 4 " bcd [3:0] $end
$var reg 7 # expected_segment [6:0] $end
$var integer 32 $ bcd_value [31:0] $end
$var integer 32 % failure_count [31:0] $end
$var integer 32 & test_count [31:0] $end
$scope function expected_segments $end
$var reg 4 ' digit [3:0] $end
$upscope $end
$scope module dut $end
$var wire 4 ( bcd [3:0] $end
$var reg 7 ) segment [6:0] $end
$upscope $end
$upscope $end
$enddefinitions $end
$comment Show the parameter values. $end
$dumpall
$end
#0
$dumpvars
b111111 )
b0 (
bx '
b0 &
b0 %
b0 $
bx #
b0 "
b111111 !
$end
#1000
b110 !
b110 )
b1 "
b1 (
b1 $
b1 &
b111111 #
b0 '
#2000
b1011011 !
b1011011 )
b10 "
b10 (
b10 $
b10 &
b110 #
b1 '
#3000
b1001111 !
b1001111 )
b11 "
b11 (
b11 $
b11 &
b1011011 #
b10 '
#4000
b1100110 !
b1100110 )
b100 "
b100 (
b100 $
b100 &
b1001111 #
b11 '
#5000
b1101101 !
b1101101 )
b101 "
b101 (
b101 $
b101 &
b1100110 #
b100 '
#6000
b1111101 !
b1111101 )
b110 "
b110 (
b110 $
b110 &
b1101101 #
b101 '
#7000
b111 !
b111 )
b111 "
b111 (
b111 $
b111 &
b1111101 #
b110 '
#8000
b1111111 !
b1111111 )
b1000 "
b1000 (
b1000 $
b1000 &
b111 #
b111 '
#9000
b1101111 !
b1101111 )
b1001 "
b1001 (
b1001 $
b1001 &
b1111111 #
b1000 '
#10000
b1010 $
b1010 &
b1101111 #
b1001 '
