DAY2/Assignment 5/4bit_comparator.v
/*
 * 4-bit magnitude comparator
 * Compares unsigned values A and B from 0 to F.
 */

module comparator_4bit (
	input  [3:0] a,
	input  [3:0] b,
	output reg  a_greater,
	output reg  b_greater,
	output reg  equal
);

	always @(*) begin
		a_greater = 1'b0;
		b_greater = 1'b0;
		equal = 1'b0;

		if (a[3] != b[3]) begin
			a_greater = a[3];
			b_greater = b[3];
		end else if (a[2] != b[2]) begin
			a_greater = a[2];
			b_greater = b[2];
		end else if (a[1] != b[1]) begin
			a_greater = a[1];
			b_greater = b[1];
		end else if (a[0] != b[0]) begin
			a_greater = a[0];
			b_greater = b[0];
		end else begin
			equal = 1'b1;
		end
	end

endmodule

DAY2/Assignment 5/4bit_comparator_tb.v
/*
 * Testbench for the 4-bit magnitude comparator.
 * Runs random smoke tests followed by exhaustive tests of all input pairs.
 */

`timescale 1ns/1ps

module comparator_4bit_tb;

    reg  [3:0] a;
    reg  [3:0] b;
    wire       a_greater;
    wire       b_greater;
    wire       equal;

    integer input_value_a;
    integer input_value_b;
    integer random_value_a;
    integer random_value_b;
    integer random_test_index;
    integer random_seed;
    integer test_count;
    integer failure_count;

    comparator_4bit dut (
        .a(a),
        .b(b),
        .a_greater(a_greater),
        .b_greater(b_greater),
        .equal(equal)
    );

    task automatic check_case;
        input [3:0] test_a;
        input [3:0] test_b;
        begin
            a = test_a;
            b = test_b;
            #1;

            test_count = test_count + 1;

            if (test_a > test_b) begin
                $display("Test %0d: A=%0d, B=%0d -> A > B | result: a_greater=%b b_greater=%b equal=%b",
                         test_count, test_a, test_b, a_greater, b_greater, equal);
                if ({a_greater, b_greater, equal} !== 3'b100) begin
                    $display("FAIL: expected A > B, got %b", {a_greater, b_greater, equal});
                    failure_count = failure_count + 1;
                end
            end else if (test_a < test_b) begin
                $display("Test %0d: A=%0d, B=%0d -> A < B | result: a_greater=%b b_greater=%b equal=%b",
                         test_count, test_a, test_b, a_greater, b_greater, equal);
                if ({a_greater, b_greater, equal} !== 3'b010) begin
                    $display("FAIL: expected A < B, got %b", {a_greater, b_greater, equal});
                    failure_count = failure_count + 1;
                end
            end else begin
                $display("Test %0d: A=%0d, B=%0d -> A == B | result: a_greater=%b b_greater=%b equal=%b",
                         test_count, test_a, test_b, a_greater, b_greater, equal);
                if ({a_greater, b_greater, equal} !== 3'b001) begin
                    $display("FAIL: expected A == B, got %b", {a_greater, b_greater, equal});
                    failure_count = failure_count + 1;
                end
            end
        end
    endtask

    initial begin
        $dumpfile("4bit_comparator_tb.vcd");
        $dumpvars(0, comparator_4bit_tb);

        test_count = 0;
        failure_count = 0;
        random_seed = 32'h1ACE_B00C;

        $display("Starting 20 deterministic random comparator tests...");
        for (random_test_index = 0; random_test_index < 20; random_test_index = random_test_index + 1) begin
            random_value_a = $random(random_seed) & 4'hf;
            random_value_b = $random(random_seed) & 4'hf;
            check_case(random_value_a, random_value_b);
        end

        $display("Starting 256-case exhaustive comparator test...");

        for (input_value_a = 0; input_value_a < 16; input_value_a = input_value_a + 1) begin
            for (input_value_b = 0; input_value_b < 16; input_value_b = input_value_b + 1) begin
                check_case(input_value_a, input_value_b);
            end
        end

        if (failure_count == 0) begin
            $display("PASS: %0d random and exhaustive comparator tests completed successfully.", test_count);
        end else begin
            $display("FAIL: %0d of %0d comparator tests failed.", failure_count, test_count);
            $fatal(1);
        end

        $finish;
    end

endmodule

DAY2/Assignment 5/4bit_comparator_tb.vcd
$date
	Tue Sep 22 23:06:14 2026
$end
$version
	Icarus Verilog
$end
$timescale
	1ps
$end
$scope module comparator_4bit_tb $end
$var wire 1 ! equal $end
$var wire 1 " b_greater $end
$var wire 1 # a_greater $end
$var reg 4 $ a [3:0] $end
$var reg 4 % b [3:0] $end
$var integer 32 & failure_count [31:0] $end
$var integer 32 ' input_value_a [31:0] $end
$var integer 32 ( input_value_b [31:0] $end
$var integer 32 ) random_seed [31:0] $end
$var integer 32 * random_test_index [31:0] $end
$var integer 32 + random_value_a [31:0] $end
$var integer 32 , random_value_b [31:0] $end
$var integer 32 - test_count [31:0] $end
$scope module dut $end
$var wire 4 . a [3:0] $end
$var wire 4 / b [3:0] $end
$var reg 1 # a_greater $end
$var reg 1 " b_greater $end
$var reg 1 ! equal $end
$upscope $end
$scope task check_case $end
$upscope $end
$upscope $end
$enddefinitions $end
$comment Show the parameter values. $end
$dumpall
$end
#0
$dumpvars
b1000 /
b1100 .
b0 -
b1000 ,
b1100 +
b0 *
b1100100011000001100011110111010 )
bx (
bx '
b0 &
b1000 %
b1100 $
1#
0"
0!
$end
#1000
1"
0#
b1111 %
b1111 /
b110 $
b110 .
b1111 ,
b110 +
b10101111100000001100011010011000 )
b1 *
b1 -
#2000
1"
b110 %
b110 /
b101 $
b101 .
b110 ,
b101 +
b1011011011010101110110000100110 )
b10 *
b10 -
#3000
1#
0"
b100 %
b100 /
b1101 $
b1101 .
b100 ,
b1101 +
b1000010000010100110001111100100 )
b11 *
b11 -
#4000
1#
b1000 %
b1000 /
b1010 $
b1010 .
b1000 ,
b1010 +
b10100100000101100010010101010010 )
b100 *
b100 -
#5000
1#
b1 %
b1 /
b101 $
b101 .
b1 ,
b101 +
b1001000111100001101001111110000 )
b101 *
b101 -
#6000
1#
b101 %
b101 /
b1111 $
b1111 .
b101 ,
b1111 +
b11001010110000111001111100111110 )
b110 *
b110 -
#7000
1#
b100 %
b100 /
b1001 $
b1001 .
b100 ,
b1001 +
b101010000011000010001010111100 )
b111 *
b111 -
#8000
1"
0#
b1001 %
b1001 /
b1000 $
b1000 .
b1001 ,
b1000 +
b11010100100101010100010111101010 )
b1000 *
b1000 -
#9000
1#
0"
b101 %
b101 /
b1011 $
b1011 .
b101 ,
b1011 +
b1111010100100110001110001001000 )
b1001 *
b1001 -
#10000
1#
b10 %
b10 /
b1001 $
b1001 .
b10 ,
b1001 +
b1001010110011100010101010110 )
b1010 *
b1010 -
#11000
1"
0#
b1011 %
b1011 /
b10 $
b10 .
b1011 ,
b10 +
b11101111001110100110010010100 )
b1011 *
b1011 -
#12000
1#
0"
b100 %
b100 /
b1011 $
b1011 .
b100 ,
b1011 +
b11101010001110001000100110000010 )
b1100 *
b1100 -
#13000
1#
b1110 %
b1110 /
b1111 $
b1111 .
b1110 ,
b1111 +
b1111001000001111111110100000 )
b1101 *
b1101 -
#14000
1#
b10 %
b10 /
b100 $
b100 .
b10 ,
b100 +
b1000111011011111001101110 )
b1110 *
b1110 -
#15000
1#
b1011 $
b1011 .
b1011 +
b1100001010110110100000101101100 )
b1111 *
b1111 -
#16000
1"
0#
b1001 %
b1001 /
b11 $
b11 .
b1001 ,
b11 +
b11110100111001100101000000011010 )
b10000 *
b10000 -
#17000
1#
0"
b101 %
b101 /
b1101 $
b1101 .
b101 ,
b1101 +
b11000010101111111101110111111000 )
b10001 *
b10001 -
#18000
1#
b1100 %
b1100 /
b1111 $
b1111 .
b1100 ,
b1111 +
b1110010010111110101010000110 )
b10010 *
b10010 -
#19000
1"
0#
b0 $
b0 .
b0 +
b10001110010100110110000101000100 )
b10011 *
b10011 -
#20000
1!
0"
b0 %
b0 /
b0 (
b0 '
b10100 *
b10100 -
#21000
1"
0!
b1 %
b1 /
b1 (
b10101 -
#22000
1"
b10 %
b10 /
b10 (
b10110 -
#23000
1"
b11 %
b11 /
b11 (
b10111 -
#24000
1"
b100 %
b100 /
b100 (
b11000 -
#25000
1"
b101 %
b101 /
b101 (
b11001 -
#26000
1"
b110 %
b110 /
b110 (
b11010 -
#27000
1"
b111 %
b111 /
b111 (
b11011 -
#28000
1"
b1000 %
b1000 /
b1000 (
b11100 -
#29000
1"
b1001 %
b1001 /
b1001 (
b11101 -
#30000
1"
b1010 %
b1010 /
b1010 (
b11110 -
#31000
1"
b1011 %
b1011 /
b1011 (
b11111 -
#32000
1"
b1100 %
b1100 /
b1100 (
b100000 -
#33000
1"
b1101 %
b1101 /
b1101 (
b100001 -
#34000
1"
b1110 %
b1110 /
b1110 (
b100010 -
#35000
1"
b1111 %
b1111 /
b1111 (
b100011 -
#36000
1#
0"
b0 %
b0 /
b1 $
b1 .
b1 '
b0 (
b100100 -
#37000
1!
0#
b1 %
b1 /
b1 (
b100101 -
#38000
1"
0!
b10 %
b10 /
b10 (
b100110 -
#39000
1"
b11 %
b11 /
b11 (
b100111 -
#40000
1"
b100 %
b100 /
b100 (
b101000 -
#41000
1"
b101 %
b101 /
b101 (
b101001 -
#42000
1"
b110 %
b110 /
b110 (
b101010 -
#43000
1"
b111 %
b111 /
b111 (
b101011 -
#44000
1"
b1000 %
b1000 /
b1000 (
b101100 -
#45000
1"
b1001 %
b1001 /
b1001 (
b101101 -
#46000
1"
b1010 %
b1010 /
b1010 (
b101110 -
#47000
1"
b1011 %
b1011 /
b1011 (
b101111 -
#48000
1"
b1100 %
b1100 /
b1100 (
b110000 -
#49000
1"
b1101 %
b1101 /
b1101 (
b110001 -
#50000
1"
b1110 %
b1110 /
b1110 (
b110010 -
#51000
1"
b1111 %
b1111 /
b1111 (
b110011 -
#52000
1#
0"
b0 %
b0 /
b10 $
b10 .
b10 '
b0 (
b110100 -
#53000
1#
b1 %
b1 /
b1 (
b110101 -
#54000
1!
0#
b10 %
b10 /
b10 (
b110110 -
#55000
1"
0!
b11 %
b11 /
b11 (
b110111 -
#56000
1"
b100 %
b100 /
b100 (
b111000 -
#57000
1"
b101 %
b101 /
b101 (
b111001 -
#58000
1"
b110 %
b110 /
b110 (
b111010 -
#59000
1"
b111 %
b111 /
b111 (
b111011 -
#60000
1"
b1000 %
b1000 /
b1000 (
b111100 -
#61000
1"
b1001 %
b1001 /
b1001 (
b111101 -
#62000
1"
b1010 %
b1010 /
b1010 (
b111110 -
#63000
1"
b1011 %
b1011 /
b1011 (
b111111 -
#64000
1"
b1100 %
b1100 /
b1100 (
b1000000 -
#65000
1"
b1101 %
b1101 /
b1101 (
b1000001 -
#66000
1"
b1110 %
b1110 /
b1110 (
b1000010 -
#67000
1"
b1111 %
b1111 /
b1111 (
b1000011 -
#68000
1#
0"
b0 %
b0 /
b11 $
b11 .
b11 '
b0 (
b1000100 -
#69000
1#
b1 %
b1 /
b1 (
b1000101 -
#70000
1#
b10 %
b10 /
b10 (
b1000110 -
#71000
1!
0#
b11 %
b11 /
b11 (
b1000111 -
#72000
1"
0!
b100 %
b100 /
b100 (
b1001000 -
#73000
1"
b101 %
b101 /
b101 (
b1001001 -
#74000
1"
b110 %
b110 /
b110 (
b1001010 -
#75000
1"
b111 %
b111 /
b111 (
b1001011 -
#76000
1"
b1000 %
b1000 /
b1000 (
b1001100 -
#77000
1"
b1001 %
b1001 /
b1001 (
b1001101 -
#78000
1"
b1010 %
b1010 /
b1010 (
b1001110 -
#79000
1"
b1011 %
b1011 /
b1011 (
b1001111 -
#80000
1"
b1100 %
b1100 /
b1100 (
b1010000 -
#81000
1"
b1101 %
b1101 /
b1101 (
b1010001 -
#82000
1"
b1110 %
b1110 /
b1110 (
b1010010 -
#83000
1"
b1111 %
b1111 /
b1111 (
b1010011 -
#84000
1#
0"
b0 %
b0 /
b100 $
b100 .
b100 '
b0 (
b1010100 -
#85000
1#
b1 %
b1 /
b1 (
b1010101 -
#86000
1#
b10 %
b10 /
b10 (
b1010110 -
#87000
1#
b11 %
b11 /
b11 (
b1010111 -
#88000
1!
0#
b100 %
b100 /
b100 (
b1011000 -
#89000
1"
0!
b101 %
b101 /
b101 (
b1011001 -
#90000
1"
b110 %
b110 /
b110 (
b1011010 -
#91000
1"
b111 %
b111 /
b111 (
b1011011 -
#92000
1"
b1000 %
b1000 /
b1000 (
b1011100 -
#93000
1"
b1001 %
b1001 /
b1001 (
b1011101 -
#94000
1"
b1010 %
b1010 /
b1010 (
b1011110 -
#95000
1"
b1011 %
b1011 /
b1011 (
b1011111 -
#96000
1"
b1100 %
b1100 /
b1100 (
b1100000 -
#97000
1"
b1101 %
b1101 /
b1101 (
b1100001 -
#98000
1"
b1110 %
b1110 /
b1110 (
b1100010 -
#99000
1"
b1111 %
b1111 /
b1111 (
b1100011 -
#100000
1#
0"
b0 %
b0 /
b101 $
b101 .
b101 '
b0 (
b1100100 -
#101000
1#
b1 %
b1 /
b1 (
b1100101 -
#102000
1#
b10 %
b10 /
b10 (
b1100110 -
#103000
1#
b11 %
b11 /
b11 (
b1100111 -
#104000
1#
b100 %
b100 /
b100 (
b1101000 -
#105000
1!
0#
b101 %
b101 /
b101 (
b1101001 -
#106000
1"
0!
b110 %
b110 /
b110 (
b1101010 -
#107000
1"
b111 %
b111 /
b111 (
b1101011 -
#108000
1"
b1000 %
b1000 /
b1000 (
b1101100 -
#109000
1"
b1001 %
b1001 /
b1001 (
b1101101 -
#110000
1"
b1010 %
b1010 /
b1010 (
b1101110 -
#111000
1"
b1011 %
b1011 /
b1011 (
b1101111 -
#112000
1"
b1100 %
b1100 /
b1100 (
b1110000 -
#113000
1"
b1101 %
b1101 /
b1101 (
b1110001 -
#114000
1"
b1110 %
b1110 /
b1110 (
b1110010 -
#115000
1"
b1111 %
b1111 /
b1111 (
b1110011 -
#116000
1#
0"
b0 %
b0 /
b110 $
b110 .
b110 '
b0 (
b1110100 -
#117000
1#
b1 %
b1 /
b1 (
b1110101 -
#118000
1#
b10 %
b10 /
b10 (
b1110110 -
#119000
1#
b11 %
b11 /
b11 (
b1110111 -
#120000
1#
b100 %
b100 /
b100 (
b1111000 -
#121000
1#
b101 %
b101 /
b101 (
b1111001 -
#122000
1!
0#
b110 %
b110 /
b110 (
b1111010 -
#123000
1"
0!
b111 %
b111 /
b111 (
b1111011 -
#124000
1"
b1000 %
b1000 /
b1000 (
b1111100 -
#125000
1"
b1001 %
b1001 /
b1001 (
b1111101 -
#126000
1"
b1010 %
b1010 /
b1010 (
b1111110 -
#127000
1"
b1011 %
b1011 /
b1011 (
b1111111 -
#128000
1"
b1100 %
b1100 /
b1100 (
b10000000 -
#129000
1"
b1101 %
b1101 /
b1101 (
b10000001 -
#130000
1"
b1110 %
b1110 /
b1110 (
b10000010 -
#131000
1"
b1111 %
b1111 /
b1111 (
b10000011 -
#132000
1#
0"
b0 %
b0 /
b111 $
b111 .
b111 '
b0 (
b10000100 -
#133000
1#
b1 %
b1 /
b1 (
b10000101 -
#134000
1#
b10 %
b10 /
b10 (
b10000110 -
#135000
1#
b11 %
b11 /
b11 (
b10000111 -
#136000
1#
b100 %
b100 /
b100 (
b10001000 -
#137000
1#
b101 %
b101 /
b101 (
b10001001 -
#138000
1#
b110 %
b110 /
b110 (
b10001010 -
#139000
1!
0#
b111 %
b111 /
b111 (
b10001011 -
#140000
1"
0!
b1000 %
b1000 /
b1000 (
b10001100 -
#141000
1"
b1001 %
b1001 /
b1001 (
b10001101 -
#142000
1"
b1010 %
b1010 /
b1010 (
b10001110 -
#143000
1"
b1011 %
b1011 /
b1011 (
b10001111 -
#144000
1"
b1100 %
b1100 /
b1100 (
b10010000 -
#145000
1"
b1101 %
b1101 /
b1101 (
b10010001 -
#146000
1"
b1110 %
b1110 /
b1110 (
b10010010 -
#147000
1"
b1111 %
b1111 /
b1111 (
b10010011 -
#148000
1#
0"
b0 %
b0 /
b1000 $
b1000 .
b1000 '
b0 (
b10010100 -
#149000
1#
b1 %
b1 /
b1 (
b10010101 -
#150000
1#
b10 %
b10 /
b10 (
b10010110 -
#151000
1#
b11 %
b11 /
b11 (
b10010111 -
#152000
1#
b100 %
b100 /
b100 (
b10011000 -
#153000
1#
b101 %
b101 /
b101 (
b10011001 -
#154000
1#
b110 %
b110 /
b110 (
b10011010 -
#155000
1#
b111 %
b111 /
b111 (
b10011011 -
#156000
1!
0#
b1000 %
b1000 /
b1000 (
b10011100 -
#157000
1"
0!
b1001 %
b1001 /
b1001 (
b10011101 -
#158000
1"
b1010 %
b1010 /
b1010 (
b10011110 -
#159000
1"
b1011 %
b1011 /
b1011 (
b10011111 -
#160000
1"
b1100 %
b1100 /
b1100 (
b10100000 -
#161000
1"
b1101 %
b1101 /
b1101 (
b10100001 -
#162000
1"
b1110 %
b1110 /
b1110 (
b10100010 -
#163000
1"
b1111 %
b1111 /
b1111 (
b10100011 -
#164000
1#
0"
b0 %
b0 /
b1001 $
b1001 .
b1001 '
b0 (
b10100100 -
#165000
1#
b1 %
b1 /
b1 (
b10100101 -
#166000
1#
b10 %
b10 /
b10 (
b10100110 -
#167000
1#
b11 %
b11 /
b11 (
b10100111 -
#168000
1#
b100 %
b100 /
b100 (
b10101000 -
#169000
1#
b101 %
b101 /
b101 (
b10101001 -
#170000
1#
b110 %
b110 /
b110 (
b10101010 -
#171000
1#
b111 %
b111 /
b111 (
b10101011 -
#172000
1#
b1000 %
b1000 /
b1000 (
b10101100 -
#173000
1!
0#
b1001 %
b1001 /
b1001 (
b10101101 -
#174000
1"
0!
b1010 %
b1010 /
b1010 (
b10101110 -
#175000
1"
b1011 %
b1011 /
b1011 (
b10101111 -
#176000
1"
b1100 %
b1100 /
b1100 (
b10110000 -
#177000
1"
b1101 %
b1101 /
b1101 (
b10110001 -
#178000
1"
b1110 %
b1110 /
b1110 (
b10110010 -
#179000
1"
b1111 %
b1111 /
b1111 (
b10110011 -
#180000
1#
0"
b0 %
b0 /
b1010 $
b1010 .
b1010 '
b0 (
b10110100 -
#181000
1#
b1 %
b1 /
b1 (
b10110101 -
#182000
1#
b10 %
b10 /
b10 (
b10110110 -
#183000
1#
b11 %
b11 /
b11 (
b10110111 -
#184000
1#
b100 %
b100 /
b100 (
b10111000 -
#185000
1#
b101 %
b101 /
b101 (
b10111001 -
#186000
1#
b110 %
b110 /
b110 (
b10111010 -
#187000
1#
b111 %
b111 /
b111 (
b10111011 -
#188000
1#
b1000 %
b1000 /
b1000 (
b10111100 -
#189000
1#
b1001 %
b1001 /
b1001 (
b10111101 -
#190000
1!
0#
b1010 %
b1010 /
b1010 (
b10111110 -
#191000
1"
0!
b1011 %
b1011 /
b1011 (
b10111111 -
#192000
1"
b1100 %
b1100 /
b1100 (
b11000000 -
#193000
1"
b1101 %
b1101 /
b1101 (
b11000001 -
#194000
1"
b1110 %
b1110 /
b1110 (
b11000010 -
#195000
1"
b1111 %
b1111 /
b1111 (
b11000011 -
#196000
1#
0"
b0 %
b0 /
b1011 $
b1011 .
b1011 '
b0 (
b11000100 -
#197000
1#
b1 %
b1 /
b1 (
b11000101 -
#198000
1#
b10 %
b10 /
b10 (
b11000110 -
#199000
1#
b11 %
b11 /
b11 (
b11000111 -
#200000
1#
b100 %
b100 /
b100 (
b11001000 -
#201000
1#
b101 %
b101 /
b101 (
b11001001 -
#202000
1#
b110 %
b110 /
b110 (
b11001010 -
#203000
1#
b111 %
b111 /
b111 (
b11001011 -
#204000
1#
b1000 %
b1000 /
b1000 (
b11001100 -
#205000
1#
b1001 %
b1001 /
b1001 (
b11001101 -
#206000
1#
b1010 %
b1010 /
b1010 (
b11001110 -
#207000
1!
0#
b1011 %
b1011 /
b1011 (
b11001111 -
#208000
1"
0!
b1100 %
b1100 /
b1100 (
b11010000 -
#209000
1"
b1101 %
b1101 /
b1101 (
b11010001 -
#210000
1"
b1110 %
b1110 /
b1110 (
b11010010 -
#211000
1"
b1111 %
b1111 /
b1111 (
b11010011 -
#212000
1#
0"
b0 %
b0 /
b1100 $
b1100 .
b1100 '
b0 (
b11010100 -
#213000
1#
b1 %
b1 /
b1 (
b11010101 -
#214000
1#
b10 %
b10 /
b10 (
b11010110 -
#215000
1#
b11 %
b11 /
b11 (
b11010111 -
#216000
1#
b100 %
b100 /
b100 (
b11011000 -
#217000
1#
b101 %
b101 /
b101 (
b11011001 -
#218000
1#
b110 %
b110 /
b110 (
b11011010 -
#219000
1#
b111 %
b111 /
b111 (
b11011011 -
#220000
1#
b1000 %
b1000 /
b1000 (
b11011100 -
#221000
1#
b1001 %
b1001 /
b1001 (
b11011101 -
#222000
1#
b1010 %
b1010 /
b1010 (
b11011110 -
#223000
1#
b1011 %
b1011 /
b1011 (
b11011111 -
#224000
1!
0#
b1100 %
b1100 /
b1100 (
b11100000 -
#225000
1"
0!
b1101 %
b1101 /
b1101 (
b11100001 -
#226000
1"
b1110 %
b1110 /
b1110 (
b11100010 -
#227000
1"
b1111 %
b1111 /
b1111 (
b11100011 -
#228000
1#
0"
b0 %
b0 /
b1101 $
b1101 .
b1101 '
b0 (
b11100100 -
#229000
1#
b1 %
b1 /
b1 (
b11100101 -
#230000
1#
b10 %
b10 /
b10 (
b11100110 -
#231000
1#
b11 %
b11 /
b11 (
b11100111 -
#232000
1#
b100 %
b100 /
b100 (
b11101000 -
#233000
1#
b101 %
b101 /
b101 (
b11101001 -
#234000
1#
b110 %
b110 /
b110 (
b11101010 -
#235000
1#
b111 %
b111 /
b111 (
b11101011 -
#236000
1#
b1000 %
b1000 /
b1000 (
b11101100 -
#237000
1#
b1001 %
b1001 /
b1001 (
b11101101 -
#238000
1#
b1010 %
b1010 /
b1010 (
b11101110 -
#239000
1#
b1011 %
b1011 /
b1011 (
b11101111 -
#240000
1#
b1100 %
b1100 /
b1100 (
b11110000 -
#241000
1!
0#
b1101 %
b1101 /
b1101 (
b11110001 -
#242000
1"
0!
b1110 %
b1110 /
b1110 (
b11110010 -
#243000
1"
b1111 %
b1111 /
b1111 (
b11110011 -
#244000
1#
0"
b0 %
b0 /
b1110 $
b1110 .
b1110 '
b0 (
b11110100 -
#245000
1#
b1 %
b1 /
b1 (
b11110101 -
#246000
1#
b10 %
b10 /
b10 (
b11110110 -
#247000
1#
b11 %
b11 /
b11 (
b11110111 -
#248000
1#
b100 %
b100 /
b100 (
b11111000 -
#249000
1#
b101 %
b101 /
b101 (
b11111001 -
#250000
1#
b110 %
b110 /
b110 (
b11111010 -
#251000
1#
b111 %
b111 /
b111 (
b11111011 -
#252000
1#
b1000 %
b1000 /
b1000 (
b11111100 -
#253000
1#
b1001 %
b1001 /
b1001 (
b11111101 -
#254000
1#
b1010 %
b1010 /
b1010 (
b11111110 -
#255000
1#
b1011 %
b1011 /
b1011 (
b11111111 -
#256000
1#
b1100 %
b1100 /
b1100 (
b100000000 -
#257000
1#
b1101 %
b1101 /
b1101 (
b100000001 -
#258000
1!
0#
b1110 %
b1110 /
b1110 (
b100000010 -
#259000
1"
0!
b1111 %
b1111 /
b1111 (
b100000011 -
#260000
1#
0"
b0 %
b0 /
b1111 $
b1111 .
b1111 '
b0 (
b100000100 -
#261000
1#
b1 %
b1 /
b1 (
b100000101 -
#262000
1#
b10 %
b10 /
b10 (
b100000110 -
#263000
1#
b11 %
b11 /
b11 (
b100000111 -
#264000
1#
b100 %
b100 /
b100 (
b100001000 -
#265000
1#
b101 %
b101 /
b101 (
b100001001 -
#266000
1#
b110 %
b110 /
b110 (
b100001010 -
#267000
1#
b111 %
b111 /
b111 (
b100001011 -
#268000
1#
b1000 %
b1000 /
b1000 (
b100001100 -
#269000
1#
b1001 %
b1001 /
b1001 (
b100001101 -
#270000
1#
b1010 %
b1010 /
b1010 (
b100001110 -
#271000
1#
b1011 %
b1011 /
b1011 (
b100001111 -
#272000
1#
b1100 %
b1100 /
b1100 (
b100010000 -
#273000
1#
b1101 %
b1101 /
b1101 (
b100010001 -
#274000
1#
b1110 %
b1110 /
b1110 (
b100010010 -
#275000
1!
0#
b1111 %
b1111 /
b1111 (
b100010011 -
#276000
b10000 '
b10000 (
b100010100 -
