DAY3/Assignment 6/mealy_fsm_detect_1001.v
`timescale 1ns/1ps

module mealy_fsm_detect_1001 (
	input  wire clk,
	input  wire reset,
	input  wire data_in,
	output reg  detected
);

	localparam [1:0] S0 = 2'b00,
					 S1 = 2'b01,
					 S2 = 2'b10,
					 S3 = 2'b11;

	reg [1:0] PS, NS;

	always @(posedge clk) begin
		if (reset)
			PS <= S0;
		else
			PS <= NS;
	end

	always @(PS or data_in) begin
		NS = S0;

		case (PS)
			S0: begin
				NS = data_in ? S1 : S0;
			end

			S1: begin
				NS = data_in ? S1 : S2;
			end

			S2: begin
				NS = data_in ? S1 : S3;
			end

			S3: begin
				NS = data_in ? S1 : S0;
			end

			default: NS = S0;
		endcase
	end

	always @(PS or data_in) begin
		case (PS)
			S0, S1, S2: detected = 1'b0;
			S3: detected = data_in;
			default: detected = 1'b0;
		endcase
	end

endmodule

DAY3/Assignment 6/mealy_fsm_detect_1001_tb.v
`timescale 1ns/1ps

module mealy_fsm_detect_1001_tb;

    reg clk;
    reg reset;
    reg data_in;
    wire detected;
    integer error_count;
    integer expected_state;
    integer i;

    mealy_fsm_detect_1001 dut (
        .clk(clk),
        .reset(reset),
        .data_in(data_in),
        .detected(detected)
    );

    always #5 clk = ~clk;

    task send_bit;
        input bit_value;
        reg expected_detected;
        begin
            expected_detected = (expected_state == 3) && bit_value;

            @(negedge clk);
            data_in = bit_value;
            #1;
            if (detected !== expected_detected) begin
                $display("ERROR: bit=%b, detected=%b, expected=%b, state=%0d, time=%0t",
                         bit_value, detected, expected_detected, expected_state, $time);
                error_count = error_count + 1;
            end

            @(posedge clk);

            case (expected_state)
                0: expected_state = bit_value ? 1 : 0;
                1: expected_state = bit_value ? 1 : 2;
                2: expected_state = bit_value ? 1 : 3;
                3: expected_state = bit_value ? 1 : 0;
                default: expected_state = 0;
            endcase
        end
    endtask

    initial begin
        $dumpfile("mealy_fsm_detect_1001.vcd");
        $dumpvars(0, mealy_fsm_detect_1001_tb);

        clk = 1'b0;
        reset = 1'b1;
        data_in = 1'b0;
        error_count = 0;
        expected_state = 0;

        #17;
        reset = 1'b0;

        // Directed cases, followed by a reproducible randomized stream.
        send_bit(1'b1);
        send_bit(1'b0);
        send_bit(1'b0);
        send_bit(1'b1);
        send_bit(1'b1);
        send_bit(1'b0);
        send_bit(1'b0);
        send_bit(1'b1);

        for (i = 0; i < 256; i = i + 1)
            send_bit($urandom_range(0, 1));

        if (error_count == 0)
            $display("MEALY TEST PASSED: 264 directed/random bits checked");
        else
            $display("TEST FAILED: %0d error(s)", error_count);

        #10;
        $finish;
    end

endmodule

DAY3/Assignment 6/mealy_fsm_detect_1001.vcd
$date
	Thu Sep 24 21:23:15 2026
$end
$version
	Icarus Verilog
$end
$timescale
	1ps
$end
$scope module mealy_fsm_detect_1001_tb $end
$var wire 1 ! detected $end
$var reg 1 " clk $end
$var reg 1 # data_in $end
$var reg 1 $ reset $end
$var integer 32 % error_count [31:0] $end
$var integer 32 & expected_state [31:0] $end
$var integer 32 ' i [31:0] $end
$scope module dut $end
$var wire 1 " clk $end
$var wire 1 # data_in $end
$var wire 1 $ reset $end
$var parameter 2 ( S0 $end
$var parameter 2 ) S1 $end
$var parameter 2 * S2 $end
$var parameter 2 + S3 $end
$var reg 2 , NS [1:0] $end
$var reg 2 - PS [1:0] $end
$var reg 1 ! detected $end
$upscope $end
$scope task send_bit $end
$var reg 1 . bit_value $end
$var reg 1 / expected_detected $end
$upscope $end
$upscope $end
$enddefinitions $end
$comment Show the parameter values. $end
$dumpall
b11 +
b10 *
b1 )
b0 (
$end
#0
$dumpvars
x/
x.
bx -
b0 ,
bx '
b0 &
b0 %
1$
0#
0"
0!
$end
#5000
b0 -
1"
#10000
0"
#15000
1"
#17000
0/
1.
0$
#20000
b1 ,
1#
0"
#25000
b1 ,
b1 -
0.
b1 &
1"
#30000
b10 ,
0#
0"
#35000
b11 ,
b10 -
b10 &
1"
#40000
0"
#45000
b0 ,
b11 -
1/
1.
b11 &
1"
#50000
b1 ,
1!
1#
0"
#55000
0!
b1 ,
b1 -
0/
b1 &
1"
#60000
0"
#65000
0.
1"
#70000
b10 ,
0#
0"
#75000
b11 ,
b10 -
b10 &
1"
#80000
0"
#85000
b0 ,
b11 -
1/
1.
b11 &
1"
#90000
1!
b1 ,
1#
0"
#95000
b1 ,
0!
b1 -
0/
b0 '
b1 &
1"
#100000
0"
#105000
0.
b1 '
1"
#110000
b10 ,
0#
0"
#115000
b11 ,
b10 -
b10 '
b10 &
1"
#120000
0"
#125000
b0 ,
b11 -
b11 '
b11 &
1"
#130000
0"
#135000
b0 -
1.
b100 '
b0 &
1"
#140000
b1 ,
1#
0"
#145000
b1 ,
b1 -
b101 '
b1 &
1"
#150000
0"
#155000
0.
b110 '
1"
#160000
b10 ,
0#
0"
#165000
b11 ,
b10 -
b111 '
b10 &
1"
#170000
0"
#175000
b0 ,
b11 -
1/
1.
b1000 '
b11 &
1"
#180000
b1 ,
1!
1#
0"
#185000
0!
b1 ,
b1 -
0/
b1001 '
b1 &
1"
#190000
0"
#195000
b1010 '
1"
#200000
0"
#205000
b1011 '
1"
#210000
0"
#215000
b1100 '
1"
#220000
0"
#225000
b1101 '
1"
#230000
0"
#235000
b1110 '
1"
#240000
0"
#245000
0.
b1111 '
1"
#250000
b10 ,
0#
0"
#255000
b11 ,
b10 -
b10000 '
b10 &
1"
#260000
0"
#265000
b0 ,
b11 -
b10001 '
b11 &
1"
#270000
0"
#275000
b0 -
1.
b10010 '
b0 &
1"
#280000
b1 ,
1#
0"
#285000
b1 ,
b1 -
0.
b10011 '
b1 &
1"
#290000
b10 ,
0#
0"
#295000
b11 ,
b10 -
b10100 '
b10 &
1"
#300000
0"
#305000
b0 ,
b11 -
1/
1.
b10101 '
b11 &
1"
#310000
1!
b1 ,
1#
0"
#315000
b1 ,
0!
b1 -
0/
b10110 '
b1 &
1"
#320000
0"
#325000
0.
b10111 '
1"
#330000
b10 ,
0#
0"
#335000
b11 ,
b10 -
b11000 '
b10 &
1"
#340000
0"
#345000
b0 ,
b11 -
b11001 '
b11 &
1"
#350000
0"
#355000
b0 -
1.
b11010 '
b0 &
1"
#360000
b1 ,
1#
0"
#365000
b1 ,
b1 -
0.
b11011 '
b1 &
1"
#370000
b10 ,
0#
0"
#375000
b11 ,
b10 -
b11100 '
b10 &
1"
#380000
0"
#385000
b0 ,
b11 -
b11101 '
b11 &
1"
#390000
0"
#395000
b0 -
b11110 '
b0 &
1"
#400000
0"
#405000
1.
b11111 '
1"
#410000
b1 ,
1#
0"
#415000
b1 ,
b1 -
0.
b100000 '
b1 &
1"
#420000
b10 ,
0#
0"
#425000
b11 ,
b10 -
1.
b100001 '
b10 &
1"
#430000
b1 ,
1#
0"
#435000
b1 ,
b1 -
b100010 '
b1 &
1"
#440000
0"
#445000
0.
b100011 '
1"
#450000
b10 ,
0#
0"
#455000
b11 ,
b10 -
b100100 '
b10 &
1"
#460000
0"
#465000
b0 ,
b11 -
b100101 '
b11 &
1"
#470000
0"
#475000
b0 -
b100110 '
b0 &
1"
#480000
0"
#485000
b100111 '
1"
#490000
0"
#495000
1.
b101000 '
1"
#500000
b1 ,
1#
0"
#505000
b1 ,
b1 -
0.
b101001 '
b1 &
1"
#510000
b10 ,
0#
0"
#515000
b11 ,
b10 -
b101010 '
b10 &
1"
#520000
0"
#525000
b0 ,
b11 -
b101011 '
b11 &
1"
#530000
0"
#535000
b0 -
1.
b101100 '
b0 &
1"
#540000
b1 ,
1#
0"
#545000
b1 ,
b1 -
0.
b101101 '
b1 &
1"
#550000
b10 ,
0#
0"
#555000
b11 ,
b10 -
1.
b101110 '
b10 &
1"
#560000
b1 ,
1#
0"
#565000
b1 ,
b1 -
b101111 '
b1 &
1"
#570000
0"
#575000
0.
b110000 '
1"
#580000
b10 ,
0#
0"
#585000
b11 ,
b10 -
b110001 '
b10 &
1"
#590000
0"
#595000
b0 ,
b11 -
1/
1.
b110010 '
b11 &
1"
#600000
b1 ,
1!
1#
0"
#605000
0!
b1 ,
b1 -
0/
b110011 '
b1 &
1"
#610000
0"
#615000
b110100 '
1"
#620000
0"
#625000
0.
b110101 '
1"
#630000
b10 ,
0#
0"
#635000
b11 ,
b10 -
1.
b110110 '
b10 &
1"
#640000
b1 ,
1#
0"
#645000
b1 ,
b1 -
0.
b110111 '
b1 &
1"
#650000
b10 ,
0#
0"
#655000
b11 ,
b10 -
1.
b111000 '
b10 &
1"
#660000
b1 ,
1#
0"
#665000
b1 ,
b1 -
b111001 '
b1 &
1"
#670000
0"
#675000
b111010 '
1"
#680000
0"
#685000
b111011 '
1"
#690000
0"
#695000
0.
b111100 '
1"
#700000
b10 ,
0#
0"
#705000
b11 ,
b10 -
1.
b111101 '
b10 &
1"
#710000
b1 ,
1#
0"
#715000
b1 ,
b1 -
0.
b111110 '
b1 &
1"
#720000
b10 ,
0#
0"
#725000
b11 ,
b10 -
b111111 '
b10 &
1"
#730000
0"
#735000
b0 ,
b11 -
1/
1.
b1000000 '
b11 &
1"
#740000
1!
b1 ,
1#
0"
#745000
b1 ,
0!
b1 -
0/
b1000001 '
b1 &
1"
#750000
0"
#755000
0.
b1000010 '
1"
#760000
b10 ,
0#
0"
#765000
b11 ,
b10 -
1.
b1000011 '
b10 &
1"
#770000
b1 ,
1#
0"
#775000
b1 ,
b1 -
0.
b1000100 '
b1 &
1"
#780000
b10 ,
0#
0"
#785000
b11 ,
b10 -
1.
b1000101 '
b10 &
1"
#790000
b1 ,
1#
0"
#795000
b1 ,
b1 -
b1000110 '
b1 &
1"
#800000
0"
#805000
b1000111 '
1"
#810000
0"
#815000
b1001000 '
1"
#820000
0"
#825000
b1001001 '
1"
#830000
0"
#835000
b1001010 '
1"
#840000
0"
#845000
b1001011 '
1"
#850000
0"
#855000
b1001100 '
1"
#860000
0"
#865000
0.
b1001101 '
1"
#870000
b10 ,
0#
0"
#875000
b11 ,
b10 -
b1001110 '
b10 &
1"
#880000
0"
#885000
b0 ,
b11 -
b1001111 '
b11 &
1"
#890000
0"
#895000
b0 -
b1010000 '
b0 &
1"
#900000
0"
#905000
1.
b1010001 '
1"
#910000
b1 ,
1#
0"
#915000
b1 ,
b1 -
0.
b1010010 '
b1 &
1"
#920000
b10 ,
0#
0"
#925000
b11 ,
b10 -
b1010011 '
b10 &
1"
#930000
0"
#935000
b0 ,
b11 -
b1010100 '
b11 &
1"
#940000
0"
#945000
b0 -
b1010101 '
b0 &
1"
#950000
0"
#955000
1.
b1010110 '
1"
#960000
b1 ,
1#
0"
#965000
b1 ,
b1 -
b1010111 '
b1 &
1"
#970000
0"
#975000
0.
b1011000 '
1"
#980000
b10 ,
0#
0"
#985000
b11 ,
b10 -
1.
b1011001 '
b10 &
1"
#990000
b1 ,
1#
0"
#995000
b1 ,
b1 -
0.
b1011010 '
b1 &
1"
#1000000
b10 ,
0#
0"
#1005000
b11 ,
b10 -
1.
b1011011 '
b10 &
1"
#1010000
b1 ,
1#
0"
#1015000
b1 ,
b1 -
b1011100 '
b1 &
1"
#1020000
0"
#1025000
0.
b1011101 '
1"
#1030000
b10 ,
0#
0"
#1035000
b11 ,
b10 -
1.
b1011110 '
b10 &
1"
#1040000
b1 ,
1#
0"
#1045000
b1 ,
b1 -
b1011111 '
b1 &
1"
#1050000
0"
#1055000
b1100000 '
1"
#1060000
0"
#1065000
0.
b1100001 '
1"
#1070000
b10 ,
0#
0"
#1075000
b11 ,
b10 -
1.
b1100010 '
b10 &
1"
#1080000
b1 ,
1#
0"
#1085000
b1 ,
b1 -
0.
b1100011 '
b1 &
1"
#1090000
b10 ,
0#
0"
#1095000
b11 ,
b10 -
1.
b1100100 '
b10 &
1"
#1100000
b1 ,
1#
0"
#1105000
b1 ,
b1 -
b1100101 '
b1 &
1"
#1110000
0"
#1115000
0.
b1100110 '
1"
#1120000
b10 ,
0#
0"
#1125000
b11 ,
b10 -
1.
b1100111 '
b10 &
1"
#1130000
b1 ,
1#
0"
#1135000
b1 ,
b1 -
b1101000 '
b1 &
1"
#1140000
0"
#1145000
0.
b1101001 '
1"
#1150000
b10 ,
0#
0"
#1155000
b11 ,
b10 -
b1101010 '
b10 &
1"
#1160000
0"
#1165000
b0 ,
b11 -
b1101011 '
b11 &
1"
#1170000
0"
#1175000
b0 -
1.
b1101100 '
b0 &
1"
#1180000
b1 ,
1#
0"
#1185000
b1 ,
b1 -
0.
b1101101 '
b1 &
1"
#1190000
b10 ,
0#
0"
#1195000
b11 ,
b10 -
1.
b1101110 '
b10 &
1"
#1200000
b1 ,
1#
0"
#1205000
b1 ,
b1 -
0.
b1101111 '
b1 &
1"
#1210000
b10 ,
0#
0"
#1215000
b11 ,
b10 -
b1110000 '
b10 &
1"
#1220000
0"
#1225000
b0 ,
b11 -
b1110001 '
b11 &
1"
#1230000
0"
#1235000
b0 -
b1110010 '
b0 &
1"
#1240000
0"
#1245000
1.
b1110011 '
1"
#1250000
b1 ,
1#
0"
#1255000
b1 ,
b1 -
b1110100 '
b1 &
1"
#1260000
0"
#1265000
0.
b1110101 '
1"
#1270000
b10 ,
0#
0"
#1275000
b11 ,
b10 -
b1110110 '
b10 &
1"
#1280000
0"
#1285000
b0 ,
b11 -
1/
1.
b1110111 '
b11 &
1"
#1290000
b1 ,
1!
1#
0"
#1295000
0!
b1 ,
b1 -
0/
b1111000 '
b1 &
1"
#1300000
0"
#1305000
0.
b1111001 '
1"
#1310000
b10 ,
0#
0"
#1315000
b11 ,
b10 -
b1111010 '
b10 &
1"
#1320000
0"
#1325000
b0 ,
b11 -
b1111011 '
b11 &
1"
#1330000
0"
#1335000
b0 -
b1111100 '
b0 &
1"
#1340000
0"
#1345000
b1111101 '
1"
#1350000
0"
#1355000
1.
b1111110 '
1"
#1360000
b1 ,
1#
0"
#1365000
b1 ,
b1 -
b1111111 '
b1 &
1"
#1370000
0"
#1375000
0.
b10000000 '
1"
#1380000
b10 ,
0#
0"
#1385000
b11 ,
b10 -
1.
b10000001 '
b10 &
1"
#1390000
b1 ,
1#
0"
#1395000
b1 ,
b1 -
b10000010 '
b1 &
1"
#1400000
0"
#1405000
b10000011 '
1"
#1410000
0"
#1415000
b10000100 '
1"
#1420000
0"
#1425000
0.
b10000101 '
1"
#1430000
b10 ,
0#
0"
#1435000
b11 ,
b10 -
b10000110 '
b10 &
1"
#1440000
0"
#1445000
b0 ,
b11 -
b10000111 '
b11 &
1"
#1450000
0"
#1455000
b0 -
1.
b10001000 '
b0 &
1"
#1460000
b1 ,
1#
0"
#1465000
b1 ,
b1 -
b10001001 '
b1 &
1"
#1470000
0"
#1475000
0.
b10001010 '
1"
#1480000
b10 ,
0#
0"
#1485000
b11 ,
b10 -
b10001011 '
b10 &
1"
#1490000
0"
#1495000
b0 ,
b11 -
1/
1.
b10001100 '
b11 &
1"
#1500000
1!
b1 ,
1#
0"
#1505000
b1 ,
0!
b1 -
0/
0.
b10001101 '
b1 &
1"
#1510000
b10 ,
0#
0"
#1515000
b11 ,
b10 -
1.
b10001110 '
b10 &
1"
#1520000
b1 ,
1#
0"
#1525000
b1 ,
b1 -
0.
b10001111 '
b1 &
1"
#1530000
b10 ,
0#
0"
#1535000
b11 ,
b10 -
1.
b10010000 '
b10 &
1"
#1540000
b1 ,
1#
0"
#1545000
b1 ,
b1 -
b10010001 '
b1 &
1"
#1550000
0"
#1555000
0.
b10010010 '
1"
#1560000
b10 ,
0#
0"
#1565000
b11 ,
b10 -
b10010011 '
b10 &
1"
#1570000
0"
#1575000
b0 ,
b11 -
1/
1.
b10010100 '
b11 &
1"
#1580000
b1 ,
1!
1#
0"
#1585000
0!
b1 ,
b1 -
0/
0.
b10010101 '
b1 &
1"
#1590000
b10 ,
0#
0"
#1595000
b11 ,
b10 -
1.
b10010110 '
b10 &
1"
#1600000
b1 ,
1#
0"
#1605000
b1 ,
b1 -
0.
b10010111 '
b1 &
1"
#1610000
b10 ,
0#
0"
#1615000
b11 ,
b10 -
b10011000 '
b10 &
1"
#1620000
0"
#1625000
b0 ,
b11 -
1/
1.
b10011001 '
b11 &
1"
#1630000
1!
b1 ,
1#
0"
#1635000
b1 ,
0!
b1 -
0/
b10011010 '
b1 &
1"
#1640000
0"
#1645000
b10011011 '
1"
#1650000
0"
#1655000
0.
b10011100 '
1"
#1660000
b10 ,
0#
0"
#1665000
b11 ,
b10 -
1.
b10011101 '
b10 &
1"
#1670000
b1 ,
1#
0"
#1675000
b1 ,
b1 -
b10011110 '
b1 &
1"
#1680000
0"
#1685000
b10011111 '
1"
#1690000
0"
#1695000
0.
b10100000 '
1"
#1700000
b10 ,
0#
0"
#1705000
b11 ,
b10 -
1.
b10100001 '
b10 &
1"
#1710000
b1 ,
1#
0"
#1715000
b1 ,
b1 -
b10100010 '
b1 &
1"
#1720000
0"
#1725000
0.
b10100011 '
1"
#1730000
b10 ,
0#
0"
#1735000
b11 ,
b10 -
b10100100 '
b10 &
1"
#1740000
0"
#1745000
b0 ,
b11 -
b10100101 '
b11 &
1"
#1750000
0"
#1755000
b0 -
b10100110 '
b0 &
1"
#1760000
0"
#1765000
1.
b10100111 '
1"
#1770000
b1 ,
1#
0"
#1775000
b1 ,
b1 -
0.
b10101000 '
b1 &
1"
#1780000
b10 ,
0#
0"
#1785000
b11 ,
b10 -
1.
b10101001 '
b10 &
1"
#1790000
b1 ,
1#
0"
#1795000
b1 ,
b1 -
0.
b10101010 '
b1 &
1"
#1800000
b10 ,
0#
0"
#1805000
b11 ,
b10 -
1.
b10101011 '
b10 &
1"
#1810000
b1 ,
1#
0"
#1815000
b1 ,
b1 -
0.
b10101100 '
b1 &
1"
#1820000
b10 ,
0#
0"
#1825000
b11 ,
b10 -
b10101101 '
b10 &
1"
#1830000
0"
#1835000
b0 ,
b11 -
1/
1.
b10101110 '
b11 &
1"
#1840000
b1 ,
1!
1#
0"
#1845000
0!
b1 ,
b1 -
0/
0.
b10101111 '
b1 &
1"
#1850000
b10 ,
0#
0"
#1855000
b11 ,
b10 -
b10110000 '
b10 &
1"
#1860000
0"
#1865000
b0 ,
b11 -
1/
1.
b10110001 '
b11 &
1"
#1870000
1!
b1 ,
1#
0"
#1875000
b1 ,
0!
b1 -
0/
b10110010 '
b1 &
1"
#1880000
0"
#1885000
b10110011 '
1"
#1890000
0"
#1895000
b10110100 '
1"
#1900000
0"
#1905000
0.
b10110101 '
1"
#1910000
b10 ,
0#
0"
#1915000
b11 ,
b10 -
b10110110 '
b10 &
1"
#1920000
0"
#1925000
b0 ,
b11 -
1/
1.
b10110111 '
b11 &
1"
#1930000
b1 ,
1!
1#
0"
#1935000
0!
b1 ,
b1 -
0/
b10111000 '
b1 &
1"
#1940000
0"
#1945000
b10111001 '
1"
#1950000
0"
#1955000
b10111010 '
1"
#1960000
0"
#1965000
0.
b10111011 '
1"
#1970000
b10 ,
0#
0"
#1975000
b11 ,
b10 -
1.
b10111100 '
b10 &
1"
#1980000
b1 ,
1#
0"
#1985000
b1 ,
b1 -
b10111101 '
b1 &
1"
#1990000
0"
#1995000
b10111110 '
1"
#2000000
0"
#2005000
b10111111 '
1"
#2010000
0"
#2015000
b11000000 '
1"
#2020000
0"
#2025000
0.
b11000001 '
1"
#2030000
b10 ,
0#
0"
#2035000
b11 ,
b10 -
b11000010 '
b10 &
1"
#2040000
0"
#2045000
b0 ,
b11 -
1/
1.
b11000011 '
b11 &
1"
#2050000
1!
b1 ,
1#
0"
#2055000
b1 ,
0!
b1 -
0/
0.
b11000100 '
b1 &
1"
#2060000
b10 ,
0#
0"
#2065000
b11 ,
b10 -
b11000101 '
b10 &
1"
#2070000
0"
#2075000
b0 ,
b11 -
1/
1.
b11000110 '
b11 &
1"
#2080000
b1 ,
1!
1#
0"
#2085000
0!
b1 ,
b1 -
0/
0.
b11000111 '
b1 &
1"
#2090000
b10 ,
0#
0"
#2095000
b11 ,
b10 -
1.
b11001000 '
b10 &
1"
#2100000
b1 ,
1#
0"
#2105000
b1 ,
b1 -
0.
b11001001 '
b1 &
1"
#2110000
b10 ,
0#
0"
#2115000
b11 ,
b10 -
1.
b11001010 '
b10 &
1"
#2120000
b1 ,
1#
0"
#2125000
b1 ,
b1 -
0.
b11001011 '
b1 &
1"
#2130000
b10 ,
0#
0"
#2135000
b11 ,
b10 -
b11001100 '
b10 &
1"
#2140000
0"
#2145000
b0 ,
b11 -
1/
1.
b11001101 '
b11 &
1"
#2150000
1!
b1 ,
1#
0"
#2155000
b1 ,
0!
b1 -
0/
0.
b11001110 '
b1 &
1"
#2160000
b10 ,
0#
0"
#2165000
b11 ,
b10 -
b11001111 '
b10 &
1"
#2170000
0"
#2175000
b0 ,
b11 -
1/
1.
b11010000 '
b11 &
1"
#2180000
b1 ,
1!
1#
0"
#2185000
0!
b1 ,
b1 -
0/
0.
b11010001 '
b1 &
1"
#2190000
b10 ,
0#
0"
#2195000
b11 ,
b10 -
b11010010 '
b10 &
1"
#2200000
0"
#2205000
b0 ,
b11 -
b11010011 '
b11 &
1"
#2210000
0"
#2215000
b0 -
1.
b11010100 '
b0 &
1"
#2220000
b1 ,
1#
0"
#2225000
b1 ,
b1 -
0.
b11010101 '
b1 &
1"
#2230000
b10 ,
0#
0"
#2235000
b11 ,
b10 -
1.
b11010110 '
b10 &
1"
#2240000
b1 ,
1#
0"
#2245000
b1 ,
b1 -
0.
b11010111 '
b1 &
1"
#2250000
b10 ,
0#
0"
#2255000
b11 ,
b10 -
1.
b11011000 '
b10 &
1"
#2260000
b1 ,
1#
0"
#2265000
b1 ,
b1 -
0.
b11011001 '
b1 &
1"
#2270000
b10 ,
0#
0"
#2275000
b11 ,
b10 -
b11011010 '
b10 &
1"
#2280000
0"
#2285000
b0 ,
b11 -
1/
1.
b11011011 '
b11 &
1"
#2290000
1!
b1 ,
1#
0"
#2295000
b1 ,
0!
b1 -
0/
b11011100 '
b1 &
1"
#2300000
0"
#2305000
0.
b11011101 '
1"
#2310000
b10 ,
0#
0"
#2315000
b11 ,
b10 -
1.
b11011110 '
b10 &
1"
#2320000
b1 ,
1#
0"
#2325000
b1 ,
b1 -
0.
b11011111 '
b1 &
1"
#2330000
b10 ,
0#
0"
#2335000
b11 ,
b10 -
b11100000 '
b10 &
1"
#2340000
0"
#2345000
b0 ,
b11 -
1/
1.
b11100001 '
b11 &
1"
#2350000
b1 ,
1!
1#
0"
#2355000
0!
b1 ,
b1 -
0/
b11100010 '
b1 &
1"
#2360000
0"
#2365000
b11100011 '
1"
#2370000
0"
#2375000
b11100100 '
1"
#2380000
0"
#2385000
0.
b11100101 '
1"
#2390000
b10 ,
0#
0"
#2395000
b11 ,
b10 -
1.
b11100110 '
b10 &
1"
#2400000
b1 ,
1#
0"
#2405000
b1 ,
b1 -
b11100111 '
b1 &
1"
#2410000
0"
#2415000
b11101000 '
1"
#2420000
0"
#2425000
b11101001 '
1"
#2430000
0"
#2435000
b11101010 '
1"
#2440000
0"
#2445000
0.
b11101011 '
1"
#2450000
b10 ,
0#
0"
#2455000
b11 ,
b10 -
1.
b11101100 '
b10 &
1"
#2460000
b1 ,
1#
0"
#2465000
b1 ,
b1 -
0.
b11101101 '
b1 &
1"
#2470000
b10 ,
0#
0"
#2475000
b11 ,
b10 -
1.
b11101110 '
b10 &
1"
#2480000
b1 ,
1#
0"
#2485000
b1 ,
b1 -
0.
b11101111 '
b1 &
1"
#2490000
b10 ,
0#
0"
#2495000
b11 ,
b10 -
1.
b11110000 '
b10 &
1"
#2500000
b1 ,
1#
0"
#2505000
b1 ,
b1 -
0.
b11110001 '
b1 &
1"
#2510000
b10 ,
0#
0"
#2515000
b11 ,
b10 -
1.
b11110010 '
b10 &
1"
#2520000
b1 ,
1#
0"
#2525000
b1 ,
b1 -
0.
b11110011 '
b1 &
1"
#2530000
b10 ,
0#
0"
#2535000
b11 ,
b10 -
1.
b11110100 '
b10 &
1"
#2540000
b1 ,
1#
0"
#2545000
b1 ,
b1 -
b11110101 '
b1 &
1"
#2550000
0"
#2555000
0.
b11110110 '
1"
#2560000
b10 ,
0#
0"
#2565000
b11 ,
b10 -
1.
b11110111 '
b10 &
1"
#2570000
b1 ,
1#
0"
#2575000
b1 ,
b1 -
0.
b11111000 '
b1 &
1"
#2580000
b10 ,
0#
0"
#2585000
b11 ,
b10 -
b11111001 '
b10 &
1"
#2590000
0"
#2595000
b0 ,
b11 -
b11111010 '
b11 &
1"
#2600000
0"
#2605000
b0 -
1.
b11111011 '
b0 &
1"
#2610000
b1 ,
1#
0"
#2615000
b1 ,
b1 -
b11111100 '
b1 &
1"
#2620000
0"
#2625000
0.
b11111101 '
1"
#2630000
b10 ,
0#
0"
#2635000
b11 ,
b10 -
b11111110 '
b10 &
1"
#2640000
0"
#2645000
b0 ,
b11 -
1/
1.
b11111111 '
b11 &
1"
#2650000
1!
b1 ,
1#
0"
#2655000
b1 ,
0!
b1 -
b100000000 '
b1 &
1"
