DAY3/Assignment 6/moore_fsm_detect_1001_overlap.v
`timescale 1ns/1ps

module moore_fsm_detect_1001_overlap (
	input  wire clk,
	input  wire reset,
	input  wire data_in,
	output reg detected
);

	localparam [2:0] S0 = 3'b000,
					 S1 = 3'b001,
					 S2 = 3'b010,
					 S3 = 3'b011,
					 S4 = 3'b100;

	reg [2:0] PS, NS;

	always @(posedge clk) begin
		if (reset)
			PS <= S0;
		else
			PS <= NS;
	end

	always @(PS, data_in) begin
		NS = S0;

		case (PS)
			S0: begin
				NS = data_in ? S1 : S0;
			end

			S1: begin
				NS = data_in ? S1 : S2;
			end

			S2: begin
				NS = data_in ? S1 : S3;
			end

			S3: begin
				NS = data_in ? S4 : S0;
			end

			S4: begin
				NS = data_in ? S1 : S2;
			end

			default: NS = S0;
		endcase
	end

	always @(PS) begin
		case (PS)
			S0, S1, S2, S3: detected = 1'b0;
			S4: detected = 1'b1;
			default: detected = 1'b0;
		endcase
	end

endmodule

DAY3/Assignment 6/moore_fsm_detect_1001_overlap_tb.v
`timescale 1ns/1ps

module moore_fsm_detect_1001_overlap_tb;

    reg clk;
    reg reset;
    reg data_in;
    wire detected;
    integer error_count;
    integer expected_state;
    integer i;

    moore_fsm_detect_1001_overlap dut (
        .clk(clk),
        .reset(reset),
        .data_in(data_in),
        .detected(detected)
    );

    always #5 clk = ~clk;

    task send_bit;
        input bit_value;
        reg expected_detected;
        begin
            case (expected_state)
                0: expected_state = bit_value ? 1 : 0;
                1: expected_state = bit_value ? 1 : 2;
                2: expected_state = bit_value ? 1 : 3;
                3: expected_state = bit_value ? 4 : 0;
                4: expected_state = bit_value ? 1 : 2;
                default: expected_state = 0;
            endcase
            expected_detected = (expected_state == 4);

            @(negedge clk);
            data_in = bit_value;
            @(posedge clk);
            #1;
            if (detected !== expected_detected) begin
                $display("ERROR: bit=%b, detected=%b, expected=%b, state=%0d, time=%0t",
                         bit_value, detected, expected_detected, expected_state, $time);
                error_count = error_count + 1;
            end
        end
    endtask

    initial begin
        $dumpfile("moore_fsm_detect_1001_overlap.vcd");
        $dumpvars(0, moore_fsm_detect_1001_overlap_tb);

        clk = 1'b0;
        reset = 1'b1;
        data_in = 1'b0;
        error_count = 0;
        expected_state = 0;

        #17;
        reset = 1'b0;

        // The second 1001 overlaps the first through the suffix 10.
        send_bit(1'b1);
        send_bit(1'b0);
        send_bit(1'b0);
        send_bit(1'b1);
        send_bit(1'b0);
        send_bit(1'b0);
        send_bit(1'b1);

        for (i = 0; i < 256; i = i + 1)
            send_bit($urandom_range(0, 1));

        if (error_count == 0)
            $display("MOORE OVERLAP TEST PASSED: 263 directed/random bits checked");
        else
            $display("TEST FAILED: %0d error(s)", error_count);

        #10;
        $finish;
    end

endmodule

DAY3/Assignment 6/moore_fsm_detect_1001_overlap.vcd
$date
	Thu Sep 24 21:27:12 2026
$end
$version
	Icarus Verilog
$end
$timescale
	1ps
$end
$scope module moore_fsm_detect_1001_overlap_tb $end
$var wire 1 ! detected $end
$var reg 1 " clk $end
$var reg 1 # data_in $end
$var reg 1 $ reset $end
$var integer 32 % error_count [31:0] $end
$var integer 32 & expected_state [31:0] $end
$var integer 32 ' i [31:0] $end
$scope module dut $end
$var wire 1 " clk $end
$var wire 1 # data_in $end
$var wire 1 $ reset $end
$var parameter 3 ( S0 $end
$var parameter 3 ) S1 $end
$var parameter 3 * S2 $end
$var parameter 3 + S3 $end
$var parameter 3 , S4 $end
$var reg 3 - NS [2:0] $end
$var reg 3 . PS [2:0] $end
$var reg 1 ! detected $end
$upscope $end
$scope task send_bit $end
$var reg 1 / bit_value $end
$var reg 1 0 expected_detected $end
$upscope $end
$upscope $end
$enddefinitions $end
$comment Show the parameter values. $end
$dumpall
b100 ,
b11 +
b10 *
b1 )
b0 (
$end
#0
$dumpvars
x0
x/
bx .
b0 -
bx '
b0 &
b0 %
1$
0#
0"
x!
$end
#5000
0!
b0 .
1"
#10000
0"
#15000
1"
#17000
00
b1 &
1/
0$
#20000
b1 -
1#
0"
#25000
b1 -
b1 .
1"
#26000
b10 &
0/
#30000
b10 -
0#
0"
#35000
b11 -
b10 .
1"
#36000
b11 &
#40000
0"
#45000
b0 -
b11 .
1"
#46000
10
b100 &
1/
#50000
b100 -
1#
0"
#55000
1!
b1 -
b100 .
1"
#56000
00
b10 &
0/
#60000
b10 -
0#
0"
#65000
0!
b11 -
b10 .
1"
#66000
b11 &
#70000
0"
#75000
b0 -
b11 .
1"
#76000
10
b100 &
1/
#80000
b100 -
1#
0"
#85000
1!
b1 -
b100 .
1"
#86000
00
b1 &
b0 '
#90000
0"
#95000
0!
b1 -
b1 .
1"
#96000
b10 &
0/
b1 '
#100000
b10 -
0#
0"
#105000
b11 -
b10 .
1"
#106000
b11 &
b10 '
#110000
0"
#115000
b0 -
b11 .
1"
#116000
b0 &
b11 '
#120000
0"
#125000
b0 .
1"
#126000
b1 &
1/
b100 '
#130000
b1 -
1#
0"
#135000
b1 -
b1 .
1"
#136000
b101 '
#140000
0"
#145000
1"
#146000
b10 &
0/
b110 '
#150000
b10 -
0#
0"
#155000
b11 -
b10 .
1"
#156000
b11 &
b111 '
#160000
0"
#165000
b0 -
b11 .
1"
#166000
10
b100 &
1/
b1000 '
#170000
b100 -
1#
0"
#175000
1!
b1 -
b100 .
1"
#176000
00
b1 &
b1001 '
#180000
0"
#185000
0!
b1 -
b1 .
1"
#186000
b1010 '
#190000
0"
#195000
1"
#196000
b1011 '
#200000
0"
#205000
1"
#206000
b1100 '
#210000
0"
#215000
1"
#216000
b1101 '
#220000
0"
#225000
1"
#226000
b1110 '
#230000
0"
#235000
1"
#236000
b10 &
0/
b1111 '
#240000
b10 -
0#
0"
#245000
b11 -
b10 .
1"
#246000
b11 &
b10000 '
#250000
0"
#255000
b0 -
b11 .
1"
#256000
b0 &
b10001 '
#260000
0"
#265000
b0 .
1"
#266000
b1 &
1/
b10010 '
#270000
b1 -
1#
0"
#275000
b1 -
b1 .
1"
#276000
b10 &
0/
b10011 '
#280000
b10 -
0#
0"
#285000
b11 -
b10 .
1"
#286000
b11 &
b10100 '
#290000
0"
#295000
b0 -
b11 .
1"
#296000
10
b100 &
1/
b10101 '
#300000
b100 -
1#
0"
#305000
1!
b1 -
b100 .
1"
#306000
00
b1 &
b10110 '
#310000
0"
#315000
0!
b1 -
b1 .
1"
#316000
b10 &
0/
b10111 '
#320000
b10 -
0#
0"
#325000
b11 -
b10 .
1"
#326000
b11 &
b11000 '
#330000
0"
#335000
b0 -
b11 .
1"
#336000
b0 &
b11001 '
#340000
0"
#345000
b0 .
1"
#346000
b1 &
1/
b11010 '
#350000
b1 -
1#
0"
#355000
b1 -
b1 .
1"
#356000
b10 &
0/
b11011 '
#360000
b10 -
0#
0"
#365000
b11 -
b10 .
1"
#366000
b11 &
b11100 '
#370000
0"
#375000
b0 -
b11 .
1"
#376000
b0 &
b11101 '
#380000
0"
#385000
b0 .
1"
#386000
b11110 '
#390000
0"
#395000
1"
#396000
b1 &
1/
b11111 '
#400000
b1 -
1#
0"
#405000
b1 -
b1 .
1"
#406000
b10 &
0/
b100000 '
#410000
b10 -
0#
0"
#415000
b11 -
b10 .
1"
#416000
b1 &
1/
b100001 '
#420000
b1 -
1#
0"
#425000
b1 -
b1 .
1"
#426000
b100010 '
#430000
0"
#435000
1"
#436000
b10 &
0/
b100011 '
#440000
b10 -
0#
0"
#445000
b11 -
b10 .
1"
#446000
b11 &
b100100 '
#450000
0"
#455000
b0 -
b11 .
1"
#456000
b0 &
b100101 '
#460000
0"
#465000
b0 .
1"
#466000
b100110 '
#470000
0"
#475000
1"
#476000
b100111 '
#480000
0"
#485000
1"
#486000
b1 &
1/
b101000 '
#490000
b1 -
1#
0"
#495000
b1 -
b1 .
1"
#496000
b10 &
0/
b101001 '
#500000
b10 -
0#
0"
#505000
b11 -
b10 .
1"
#506000
b11 &
b101010 '
#510000
0"
#515000
b0 -
b11 .
1"
#516000
b0 &
b101011 '
#520000
0"
#525000
b0 .
1"
#526000
b1 &
1/
b101100 '
#530000
b1 -
1#
0"
#535000
b1 -
b1 .
1"
#536000
b10 &
0/
b101101 '
#540000
b10 -
0#
0"
#545000
b11 -
b10 .
1"
#546000
b1 &
1/
b101110 '
#550000
b1 -
1#
0"
#555000
b1 -
b1 .
1"
#556000
b101111 '
#560000
0"
#565000
1"
#566000
b10 &
0/
b110000 '
#570000
b10 -
0#
0"
#575000
b11 -
b10 .
1"
#576000
b11 &
b110001 '
#580000
0"
#585000
b0 -
b11 .
1"
#586000
10
b100 &
1/
b110010 '
#590000
b100 -
1#
0"
#595000
1!
b1 -
b100 .
1"
#596000
00
b1 &
b110011 '
#600000
0"
#605000
0!
b1 -
b1 .
1"
#606000
b110100 '
#610000
0"
#615000
1"
#616000
b10 &
0/
b110101 '
#620000
b10 -
0#
0"
#625000
b11 -
b10 .
1"
#626000
b1 &
1/
b110110 '
#630000
b1 -
1#
0"
#635000
b1 -
b1 .
1"
#636000
b10 &
0/
b110111 '
#640000
b10 -
0#
0"
#645000
b11 -
b10 .
1"
#646000
b1 &
1/
b111000 '
#650000
b1 -
1#
0"
#655000
b1 -
b1 .
1"
#656000
b111001 '
#660000
0"
#665000
1"
#666000
b111010 '
#670000
0"
#675000
1"
#676000
b111011 '
#680000
0"
#685000
1"
#686000
b10 &
0/
b111100 '
#690000
b10 -
0#
0"
#695000
b11 -
b10 .
1"
#696000
b1 &
1/
b111101 '
#700000
b1 -
1#
0"
#705000
b1 -
b1 .
1"
#706000
b10 &
0/
b111110 '
#710000
b10 -
0#
0"
#715000
b11 -
b10 .
1"
#716000
b11 &
b111111 '
#720000
0"
#725000
b0 -
b11 .
1"
#726000
10
b100 &
1/
b1000000 '
#730000
b100 -
1#
0"
#735000
1!
b1 -
b100 .
1"
#736000
00
b1 &
b1000001 '
#740000
0"
#745000
0!
b1 -
b1 .
1"
#746000
b10 &
0/
b1000010 '
#750000
b10 -
0#
0"
#755000
b11 -
b10 .
1"
#756000
b1 &
1/
b1000011 '
#760000
b1 -
1#
0"
#765000
b1 -
b1 .
1"
#766000
b10 &
0/
b1000100 '
#770000
b10 -
0#
0"
#775000
b11 -
b10 .
1"
#776000
b1 &
1/
b1000101 '
#780000
b1 -
1#
0"
#785000
b1 -
b1 .
1"
#786000
b1000110 '
#790000
0"
#795000
1"
#796000
b1000111 '
#800000
0"
#805000
1"
#806000
b1001000 '
#810000
0"
#815000
1"
#816000
b1001001 '
#820000
0"
#825000
1"
#826000
b1001010 '
#830000
0"
#835000
1"
#836000
b1001011 '
#840000
0"
#845000
1"
#846000
b1001100 '
#850000
0"
#855000
1"
#856000
b10 &
0/
b1001101 '
#860000
b10 -
0#
0"
#865000
b11 -
b10 .
1"
#866000
b11 &
b1001110 '
#870000
0"
#875000
b0 -
b11 .
1"
#876000
b0 &
b1001111 '
#880000
0"
#885000
b0 .
1"
#886000
b1010000 '
#890000
0"
#895000
1"
#896000
b1 &
1/
b1010001 '
#900000
b1 -
1#
0"
#905000
b1 -
b1 .
1"
#906000
b10 &
0/
b1010010 '
#910000
b10 -
0#
0"
#915000
b11 -
b10 .
1"
#916000
b11 &
b1010011 '
#920000
0"
#925000
b0 -
b11 .
1"
#926000
b0 &
b1010100 '
#930000
0"
#935000
b0 .
1"
#936000
b1010101 '
#940000
0"
#945000
1"
#946000
b1 &
1/
b1010110 '
#950000
b1 -
1#
0"
#955000
b1 -
b1 .
1"
#956000
b1010111 '
#960000
0"
#965000
1"
#966000
b10 &
0/
b1011000 '
#970000
b10 -
0#
0"
#975000
b11 -
b10 .
1"
#976000
b1 &
1/
b1011001 '
#980000
b1 -
1#
0"
#985000
b1 -
b1 .
1"
#986000
b10 &
0/
b1011010 '
#990000
b10 -
0#
0"
#995000
b11 -
b10 .
1"
#996000
b1 &
1/
b1011011 '
#1000000
b1 -
1#
0"
#1005000
b1 -
b1 .
1"
#1006000
b1011100 '
#1010000
0"
#1015000
1"
#1016000
b10 &
0/
b1011101 '
#1020000
b10 -
0#
0"
#1025000
b11 -
b10 .
1"
#1026000
b1 &
1/
b1011110 '
#1030000
b1 -
1#
0"
#1035000
b1 -
b1 .
1"
#1036000
b1011111 '
#1040000
0"
#1045000
1"
#1046000
b1100000 '
#1050000
0"
#1055000
1"
#1056000
b10 &
0/
b1100001 '
#1060000
b10 -
0#
0"
#1065000
b11 -
b10 .
1"
#1066000
b1 &
1/
b1100010 '
#1070000
b1 -
1#
0"
#1075000
b1 -
b1 .
1"
#1076000
b10 &
0/
b1100011 '
#1080000
b10 -
0#
0"
#1085000
b11 -
b10 .
1"
#1086000
b1 &
1/
b1100100 '
#1090000
b1 -
1#
0"
#1095000
b1 -
b1 .
1"
#1096000
b1100101 '
#1100000
0"
#1105000
1"
#1106000
b10 &
0/
b1100110 '
#1110000
b10 -
0#
0"
#1115000
b11 -
b10 .
1"
#1116000
b1 &
1/
b1100111 '
#1120000
b1 -
1#
0"
#1125000
b1 -
b1 .
1"
#1126000
b1101000 '
#1130000
0"
#1135000
1"
#1136000
b10 &
0/
b1101001 '
#1140000
b10 -
0#
0"
#1145000
b11 -
b10 .
1"
#1146000
b11 &
b1101010 '
#1150000
0"
#1155000
b0 -
b11 .
1"
#1156000
b0 &
b1101011 '
#1160000
0"
#1165000
b0 .
1"
#1166000
b1 &
1/
b1101100 '
#1170000
b1 -
1#
0"
#1175000
b1 -
b1 .
1"
#1176000
b10 &
0/
b1101101 '
#1180000
b10 -
0#
0"
#1185000
b11 -
b10 .
1"
#1186000
b1 &
1/
b1101110 '
#1190000
b1 -
1#
0"
#1195000
b1 -
b1 .
1"
#1196000
b10 &
0/
b1101111 '
#1200000
b10 -
0#
0"
#1205000
b11 -
b10 .
1"
#1206000
b11 &
b1110000 '
#1210000
0"
#1215000
b0 -
b11 .
1"
#1216000
b0 &
b1110001 '
#1220000
0"
#1225000
b0 .
1"
#1226000
b1110010 '
#1230000
0"
#1235000
1"
#1236000
b1 &
1/
b1110011 '
#1240000
b1 -
1#
0"
#1245000
b1 -
b1 .
1"
#1246000
b1110100 '
#1250000
0"
#1255000
1"
#1256000
b10 &
0/
b1110101 '
#1260000
b10 -
0#
0"
#1265000
b11 -
b10 .
1"
#1266000
b11 &
b1110110 '
#1270000
0"
#1275000
b0 -
b11 .
1"
#1276000
10
b100 &
1/
b1110111 '
#1280000
b100 -
1#
0"
#1285000
1!
b1 -
b100 .
1"
#1286000
00
b1 &
b1111000 '
#1290000
0"
#1295000
0!
b1 -
b1 .
1"
#1296000
b10 &
0/
b1111001 '
#1300000
b10 -
0#
0"
#1305000
b11 -
b10 .
1"
#1306000
b11 &
b1111010 '
#1310000
0"
#1315000
b0 -
b11 .
1"
#1316000
b0 &
b1111011 '
#1320000
0"
#1325000
b0 .
1"
#1326000
b1111100 '
#1330000
0"
#1335000
1"
#1336000
b1111101 '
#1340000
0"
#1345000
1"
#1346000
b1 &
1/
b1111110 '
#1350000
b1 -
1#
0"
#1355000
b1 -
b1 .
1"
#1356000
b1111111 '
#1360000
0"
#1365000
1"
#1366000
b10 &
0/
b10000000 '
#1370000
b10 -
0#
0"
#1375000
b11 -
b10 .
1"
#1376000
b1 &
1/
b10000001 '
#1380000
b1 -
1#
0"
#1385000
b1 -
b1 .
1"
#1386000
b10000010 '
#1390000
0"
#1395000
1"
#1396000
b10000011 '
#1400000
0"
#1405000
1"
#1406000
b10000100 '
#1410000
0"
#1415000
1"
#1416000
b10 &
0/
b10000101 '
#1420000
b10 -
0#
0"
#1425000
b11 -
b10 .
1"
#1426000
b11 &
b10000110 '
#1430000
0"
#1435000
b0 -
b11 .
1"
#1436000
b0 &
b10000111 '
#1440000
0"
#1445000
b0 .
1"
#1446000
b1 &
1/
b10001000 '
#1450000
b1 -
1#
0"
#1455000
b1 -
b1 .
1"
#1456000
b10001001 '
#1460000
0"
#1465000
1"
#1466000
b10 &
0/
b10001010 '
#1470000
b10 -
0#
0"
#1475000
b11 -
b10 .
1"
#1476000
b11 &
b10001011 '
#1480000
0"
#1485000
b0 -
b11 .
1"
#1486000
10
b100 &
1/
b10001100 '
#1490000
b100 -
1#
0"
#1495000
1!
b1 -
b100 .
1"
#1496000
00
b10 &
0/
b10001101 '
#1500000
b10 -
0#
0"
#1505000
0!
b11 -
b10 .
1"
#1506000
b1 &
1/
b10001110 '
#1510000
b1 -
1#
0"
#1515000
b1 -
b1 .
1"
#1516000
b10 &
0/
b10001111 '
#1520000
b10 -
0#
0"
#1525000
b11 -
b10 .
1"
#1526000
b1 &
1/
b10010000 '
#1530000
b1 -
1#
0"
#1535000
b1 -
b1 .
1"
#1536000
b10010001 '
#1540000
0"
#1545000
1"
#1546000
b10 &
0/
b10010010 '
#1550000
b10 -
0#
0"
#1555000
b11 -
b10 .
1"
#1556000
b11 &
b10010011 '
#1560000
0"
#1565000
b0 -
b11 .
1"
#1566000
10
b100 &
1/
b10010100 '
#1570000
b100 -
1#
0"
#1575000
1!
b1 -
b100 .
1"
#1576000
00
b10 &
0/
b10010101 '
#1580000
b10 -
0#
0"
#1585000
0!
b11 -
b10 .
1"
#1586000
b1 &
1/
b10010110 '
#1590000
b1 -
1#
0"
#1595000
b1 -
b1 .
1"
#1596000
b10 &
0/
b10010111 '
#1600000
b10 -
0#
0"
#1605000
b11 -
b10 .
1"
#1606000
b11 &
b10011000 '
#1610000
0"
#1615000
b0 -
b11 .
1"
#1616000
10
b100 &
1/
b10011001 '
#1620000
b100 -
1#
0"
#1625000
1!
b1 -
b100 .
1"
#1626000
00
b1 &
b10011010 '
#1630000
0"
#1635000
0!
b1 -
b1 .
1"
#1636000
b10011011 '
#1640000
0"
#1645000
1"
#1646000
b10 &
0/
b10011100 '
#1650000
b10 -
0#
0"
#1655000
b11 -
b10 .
1"
#1656000
b1 &
1/
b10011101 '
#1660000
b1 -
1#
0"
#1665000
b1 -
b1 .
1"
#1666000
b10011110 '
#1670000
0"
#1675000
1"
#1676000
b10011111 '
#1680000
0"
#1685000
1"
#1686000
b10 &
0/
b10100000 '
#1690000
b10 -
0#
0"
#1695000
b11 -
b10 .
1"
#1696000
b1 &
1/
b10100001 '
#1700000
b1 -
1#
0"
#1705000
b1 -
b1 .
1"
#1706000
b10100010 '
#1710000
0"
#1715000
1"
#1716000
b10 &
0/
b10100011 '
#1720000
b10 -
0#
0"
#1725000
b11 -
b10 .
1"
#1726000
b11 &
b10100100 '
#1730000
0"
#1735000
b0 -
b11 .
1"
#1736000
b0 &
b10100101 '
#1740000
0"
#1745000
b0 .
1"
#1746000
b10100110 '
#1750000
0"
#1755000
1"
#1756000
b1 &
1/
b10100111 '
#1760000
b1 -
1#
0"
#1765000
b1 -
b1 .
1"
#1766000
b10 &
0/
b10101000 '
#1770000
b10 -
0#
0"
#1775000
b11 -
b10 .
1"
#1776000
b1 &
1/
b10101001 '
#1780000
b1 -
1#
0"
#1785000
b1 -
b1 .
1"
#1786000
b10 &
0/
b10101010 '
#1790000
b10 -
0#
0"
#1795000
b11 -
b10 .
1"
#1796000
b1 &
1/
b10101011 '
#1800000
b1 -
1#
0"
#1805000
b1 -
b1 .
1"
#1806000
b10 &
0/
b10101100 '
#1810000
b10 -
0#
0"
#1815000
b11 -
b10 .
1"
#1816000
b11 &
b10101101 '
#1820000
0"
#1825000
b0 -
b11 .
1"
#1826000
10
b100 &
1/
b10101110 '
#1830000
b100 -
1#
0"
#1835000
1!
b1 -
b100 .
1"
#1836000
00
b10 &
0/
b10101111 '
#1840000
b10 -
0#
0"
#1845000
0!
b11 -
b10 .
1"
#1846000
b11 &
b10110000 '
#1850000
0"
#1855000
b0 -
b11 .
1"
#1856000
10
b100 &
1/
b10110001 '
#1860000
b100 -
1#
0"
#1865000
1!
b1 -
b100 .
1"
#1866000
00
b1 &
b10110010 '
#1870000
0"
#1875000
0!
b1 -
b1 .
1"
#1876000
b10110011 '
#1880000
0"
#1885000
1"
#1886000
b10110100 '
#1890000
0"
#1895000
1"
#1896000
b10 &
0/
b10110101 '
#1900000
b10 -
0#
0"
#1905000
b11 -
b10 .
1"
#1906000
b11 &
b10110110 '
#1910000
0"
#1915000
b0 -
b11 .
1"
#1916000
10
b100 &
1/
b10110111 '
#1920000
b100 -
1#
0"
#1925000
1!
b1 -
b100 .
1"
#1926000
00
b1 &
b10111000 '
#1930000
0"
#1935000
0!
b1 -
b1 .
1"
#1936000
b10111001 '
#1940000
0"
#1945000
1"
#1946000
b10111010 '
#1950000
0"
#1955000
1"
#1956000
b10 &
0/
b10111011 '
#1960000
b10 -
0#
0"
#1965000
b11 -
b10 .
1"
#1966000
b1 &
1/
b10111100 '
#1970000
b1 -
1#
0"
#1975000
b1 -
b1 .
1"
#1976000
b10111101 '
#1980000
0"
#1985000
1"
#1986000
b10111110 '
#1990000
0"
#1995000
1"
#1996000
b10111111 '
#2000000
0"
#2005000
1"
#2006000
b11000000 '
#2010000
0"
#2015000
1"
#2016000
b10 &
0/
b11000001 '
#2020000
b10 -
0#
0"
#2025000
b11 -
b10 .
1"
#2026000
b11 &
b11000010 '
#2030000
0"
#2035000
b0 -
b11 .
1"
#2036000
10
b100 &
1/
b11000011 '
#2040000
b100 -
1#
0"
#2045000
1!
b1 -
b100 .
1"
#2046000
00
b10 &
0/
b11000100 '
#2050000
b10 -
0#
0"
#2055000
0!
b11 -
b10 .
1"
#2056000
b11 &
b11000101 '
#2060000
0"
#2065000
b0 -
b11 .
1"
#2066000
10
b100 &
1/
b11000110 '
#2070000
b100 -
1#
0"
#2075000
1!
b1 -
b100 .
1"
#2076000
00
b10 &
0/
b11000111 '
#2080000
b10 -
0#
0"
#2085000
0!
b11 -
b10 .
1"
#2086000
b1 &
1/
b11001000 '
#2090000
b1 -
1#
0"
#2095000
b1 -
b1 .
1"
#2096000
b10 &
0/
b11001001 '
#2100000
b10 -
0#
0"
#2105000
b11 -
b10 .
1"
#2106000
b1 &
1/
b11001010 '
#2110000
b1 -
1#
0"
#2115000
b1 -
b1 .
1"
#2116000
b10 &
0/
b11001011 '
#2120000
b10 -
0#
0"
#2125000
b11 -
b10 .
1"
#2126000
b11 &
b11001100 '
#2130000
0"
#2135000
b0 -
b11 .
1"
#2136000
10
b100 &
1/
b11001101 '
#2140000
b100 -
1#
0"
#2145000
1!
b1 -
b100 .
1"
#2146000
00
b10 &
0/
b11001110 '
#2150000
b10 -
0#
0"
#2155000
0!
b11 -
b10 .
1"
#2156000
b11 &
b11001111 '
#2160000
0"
#2165000
b0 -
b11 .
1"
#2166000
10
b100 &
1/
b11010000 '
#2170000
b100 -
1#
0"
#2175000
1!
b1 -
b100 .
1"
#2176000
00
b10 &
0/
b11010001 '
#2180000
b10 -
0#
0"
#2185000
0!
b11 -
b10 .
1"
#2186000
b11 &
b11010010 '
#2190000
0"
#2195000
b0 -
b11 .
1"
#2196000
b0 &
b11010011 '
#2200000
0"
#2205000
b0 .
1"
#2206000
b1 &
1/
b11010100 '
#2210000
b1 -
1#
0"
#2215000
b1 -
b1 .
1"
#2216000
b10 &
0/
b11010101 '
#2220000
b10 -
0#
0"
#2225000
b11 -
b10 .
1"
#2226000
b1 &
1/
b11010110 '
#2230000
b1 -
1#
0"
#2235000
b1 -
b1 .
1"
#2236000
b10 &
0/
b11010111 '
#2240000
b10 -
0#
0"
#2245000
b11 -
b10 .
1"
#2246000
b1 &
1/
b11011000 '
#2250000
b1 -
1#
0"
#2255000
b1 -
b1 .
1"
#2256000
b10 &
0/
b11011001 '
#2260000
b10 -
0#
0"
#2265000
b11 -
b10 .
1"
#2266000
b11 &
b11011010 '
#2270000
0"
#2275000
b0 -
b11 .
1"
#2276000
10
b100 &
1/
b11011011 '
#2280000
b100 -
1#
0"
#2285000
1!
b1 -
b100 .
1"
#2286000
00
b1 &
b11011100 '
#2290000
0"
#2295000
0!
b1 -
b1 .
1"
#2296000
b10 &
0/
b11011101 '
#2300000
b10 -
0#
0"
#2305000
b11 -
b10 .
1"
#2306000
b1 &
1/
b11011110 '
#2310000
b1 -
1#
0"
#2315000
b1 -
b1 .
1"
#2316000
b10 &
0/
b11011111 '
#2320000
b10 -
0#
0"
#2325000
b11 -
b10 .
1"
#2326000
b11 &
b11100000 '
#2330000
0"
#2335000
b0 -
b11 .
1"
#2336000
10
b100 &
1/
b11100001 '
#2340000
b100 -
1#
0"
#2345000
1!
b1 -
b100 .
1"
#2346000
00
b1 &
b11100010 '
#2350000
0"
#2355000
0!
b1 -
b1 .
1"
#2356000
b11100011 '
#2360000
0"
#2365000
1"
#2366000
b11100100 '
#2370000
0"
#2375000
1"
#2376000
b10 &
0/
b11100101 '
#2380000
b10 -
0#
0"
#2385000
b11 -
b10 .
1"
#2386000
b1 &
1/
b11100110 '
#2390000
b1 -
1#
0"
#2395000
b1 -
b1 .
1"
#2396000
b11100111 '
#2400000
0"
#2405000
1"
#2406000
b11101000 '
#2410000
0"
#2415000
1"
#2416000
b11101001 '
#2420000
0"
#2425000
1"
#2426000
b11101010 '
#2430000
0"
#2435000
1"
#2436000
b10 &
0/
b11101011 '
#2440000
b10 -
0#
0"
#2445000
b11 -
b10 .
1"
#2446000
b1 &
1/
b11101100 '
#2450000
b1 -
1#
0"
#2455000
b1 -
b1 .
1"
#2456000
b10 &
0/
b11101101 '
#2460000
b10 -
0#
0"
#2465000
b11 -
b10 .
1"
#2466000
b1 &
1/
b11101110 '
#2470000
b1 -
1#
0"
#2475000
b1 -
b1 .
1"
#2476000
b10 &
0/
b11101111 '
#2480000
b10 -
0#
0"
#2485000
b11 -
b10 .
1"
#2486000
b1 &
1/
b11110000 '
#2490000
b1 -
1#
0"
#2495000
b1 -
b1 .
1"
#2496000
b10 &
0/
b11110001 '
#2500000
b10 -
0#
0"
#2505000
b11 -
b10 .
1"
#2506000
b1 &
1/
b11110010 '
#2510000
b1 -
1#
0"
#2515000
b1 -
b1 .
1"
#2516000
b10 &
0/
b11110011 '
#2520000
b10 -
0#
0"
#2525000
b11 -
b10 .
1"
#2526000
b1 &
1/
b11110100 '
#2530000
b1 -
1#
0"
#2535000
b1 -
b1 .
1"
#2536000
b11110101 '
#2540000
0"
#2545000
1"
#2546000
b10 &
0/
b11110110 '
#2550000
b10 -
0#
0"
#2555000
b11 -
b10 .
1"
#2556000
b1 &
1/
b11110111 '
#2560000
b1 -
1#
0"
#2565000
b1 -
b1 .
1"
#2566000
b10 &
0/
b11111000 '
#2570000
b10 -
0#
0"
#2575000
b11 -
b10 .
1"
#2576000
b11 &
b11111001 '
#2580000
0"
#2585000
b0 -
b11 .
1"
#2586000
b0 &
b11111010 '
#2590000
0"
#2595000
b0 .
1"
#2596000
b1 &
1/
b11111011 '
#2600000
b1 -
1#
0"
#2605000
b1 -
b1 .
1"
#2606000
b11111100 '
#2610000
0"
#2615000
1"
#2616000
b10 &
0/
b11111101 '
#2620000
b10 -
0#
0"
#2625000
b11 -
b10 .
1"
#2626000
b11 &
b11111110 '
#2630000
0"
#2635000
b0 -
b11 .
1"
#2636000
10
b100 &
1/
b11111111 '
#2640000
b100 -
1#
0"
#2645000
1!
b1 -
b100 .
1"
#2646000
b100000000 '
#2650000
0"
#2655000
0!
b1 -
b1 .
1"
