DAY2/Assignment 4/4_bit_up_down_asynchronous_reset.v
/*
 * 4-bit up/down counter with asynchronous active-high reset.
 * Reset clears the count immediately, without waiting for clk.
 */

module up_down_counter_asynchronous_reset (
    input            clk,
    input            reset,
    input            up,
    output reg [3:0] count
);

    always @(posedge clk or posedge reset) begin
        if (reset)
            count <= 4'b0000;
        else if (up)
            count <= count + 4'b0001;
        else
            count <= count - 4'b0001;
    end

endmodule

DAY2/Assignment 4/4_bit_up_down_asynchronous_reset_tb.v
/* Testbench for the asynchronous-reset up/down counter. */

`timescale 1ns/1ps

module up_down_counter_asynchronous_reset_tb;

    reg clk;
    reg reset;
    reg up;
    wire [3:0] count;
    integer test_count;
    integer failure_count;
    integer value;
    reg [87:0] mode;

    up_down_counter_asynchronous_reset dut (
        .clk(clk),
        .reset(reset),
        .up(up),
        .count(count)
    );

    always #5 clk = ~clk;

    task check_count;
        input [3:0] expected_count;
        begin
            #1;
            test_count = test_count + 1;

            if (reset)
                mode = "ASYNC RESET";
            else if (up)
                mode = "UP COUNT";
            else
                mode = "DOWN COUNT";

            if (count !== expected_count) begin
                $display("FAIL: Test %0d | %s | Expected=%b | Got=%b",
                         test_count, mode, expected_count, count);
                failure_count = failure_count + 1;
            end else begin
                $display("PASS: Test %0d | %s | Count=%b",
                         test_count, mode, count);
            end
        end
    endtask

    initial begin
        $dumpfile("4_bit_up_down_asynchronous_reset_tb.vcd");
        $dumpvars(0, up_down_counter_asynchronous_reset_tb);

        clk = 1'b0;
        reset = 1'b0;
        up = 1'b1;
        test_count = 0;
        failure_count = 0;

        $display("====================================================");
        $display("Asynchronous Reset 4-bit Up/Down Counter Test     ");
        $display("====================================================");

        #2 reset = 1'b1;
        check_count(4'd0);

        up = 1'b0;
        #2 reset = 1'b1;
        check_count(4'd0);

        reset = 1'b0;
        up = 1'b1;
        $display("\nTesting all 16 UP COUNT states...");
        for (value = 1; value <= 16; value = value + 1) begin
            @(posedge clk);
            check_count(value[3:0]);
        end

        up = 1'b0;
        $display("\nTesting all 16 DOWN COUNT states...");
        for (value = 15; value >= 0; value = value - 1) begin
            @(posedge clk);
            check_count(value[3:0]);
        end

        if (failure_count == 0)
            $display("\nPASS: %0d/%0d asynchronous-reset tests passed.",
                     test_count, test_count);
        else
            $fatal(1, "FAIL: %0d of %0d tests failed.",
                   failure_count, test_count);

        $finish;
    end

endmodule

DAY2/Assignment 4/4_bit_up_down_asynchronous_reset_tb.vcd
$date
	Wed Sep 23 06:29:41 2026
$end
$version
	Icarus Verilog
$end
$timescale
	1ps
$end
$scope module up_down_counter_asynchronous_reset_tb $end
$var wire 4 ! count [3:0] $end
$var reg 1 " clk $end
$var reg 88 # mode [87:0] $end
$var reg 1 $ reset $end
$var reg 1 % up $end
$var integer 32 & failure_count [31:0] $end
$var integer 32 ' test_count [31:0] $end
$var integer 32 ( value [31:0] $end
$scope module dut $end
$var wire 1 " clk $end
$var wire 1 $ reset $end
$var wire 1 % up $end
$var reg 4 ) count [3:0] $end
$upscope $end
$scope task check_count $end
$var reg 4 * expected_count [3:0] $end
$upscope $end
$upscope $end
$enddefinitions $end
$comment Show the parameter values. $end
$dumpall
$end
#0
$dumpvars
bx *
bx )
bx (
b0 '
b0 &
1%
0$
bx #
0"
bx !
$end
#2000
b0 !
b0 )
b0 *
1$
#3000
0%
b100000101010011010110010100111001000011001000000101001001000101010100110100010101010100 #
b1 '
#5000
1"
#6000
b1 (
1%
0$
b10 '
#10000
0"
#15000
b1 !
b1 )
b1 *
1"
#16000
b10 (
b101010101010000001000000100001101001111010101010100111001010100 #
b11 '
#20000
0"
#25000
b10 !
b10 )
b10 *
1"
#26000
b11 (
b100 '
#30000
0"
#35000
b11 !
b11 )
b11 *
1"
#36000
b100 (
b101 '
#40000
0"
#45000
b100 !
b100 )
b100 *
1"
#46000
b101 (
b110 '
#50000
0"
#55000
b101 !
b101 )
b101 *
1"
#56000
b110 (
b111 '
#60000
0"
#65000
b110 !
b110 )
b110 *
1"
#66000
b111 (
b1000 '
#70000
0"
#75000
b111 !
b111 )
b111 *
1"
#76000
b1000 (
b1001 '
#80000
0"
#85000
b1000 !
b1000 )
b1000 *
1"
#86000
b1001 (
b1010 '
#90000
0"
#95000
b1001 !
b1001 )
b1001 *
1"
#96000
b1010 (
b1011 '
#100000
0"
#105000
b1010 !
b1010 )
b1010 *
1"
#106000
b1011 (
b1100 '
#110000
0"
#115000
b1011 !
b1011 )
b1011 *
1"
#116000
b1100 (
b1101 '
#120000
0"
#125000
b1100 !
b1100 )
b1100 *
1"
#126000
b1101 (
b1110 '
#130000
0"
#135000
b1101 !
b1101 )
b1101 *
1"
#136000
b1110 (
b1111 '
#140000
0"
#145000
b1110 !
b1110 )
b1110 *
1"
#146000
b1111 (
b10000 '
#150000
0"
#155000
b1111 !
b1111 )
b1111 *
1"
#156000
b10000 (
b10001 '
#160000
0"
#165000
b0 !
b0 )
b0 *
1"
#166000
0%
b1111 (
b10010 '
#170000
0"
#175000
b1111 !
b1111 )
b1111 *
1"
#176000
b1110 (
b1000100010011110101011101001110001000000100001101001111010101010100111001010100 #
b10011 '
#180000
0"
#185000
b1110 !
b1110 )
b1110 *
1"
#186000
b1101 (
b10100 '
#190000
0"
#195000
b1101 !
b1101 )
b1101 *
1"
#196000
b1100 (
b10101 '
#200000
0"
#205000
b1100 !
b1100 )
b1100 *
1"
#206000
b1011 (
b10110 '
#210000
0"
#215000
b1011 !
b1011 )
b1011 *
1"
#216000
b1010 (
b10111 '
#220000
0"
#225000
b1010 !
b1010 )
b1010 *
1"
#226000
b1001 (
b11000 '
#230000
0"
#235000
b1001 !
b1001 )
b1001 *
1"
#236000
b1000 (
b11001 '
#240000
0"
#245000
b1000 !
b1000 )
b1000 *
1"
#246000
b111 (
b11010 '
#250000
0"
#255000
b111 !
b111 )
b111 *
1"
#256000
b110 (
b11011 '
#260000
0"
#265000
b110 !
b110 )
b110 *
1"
#266000
b101 (
b11100 '
#270000
0"
#275000
b101 !
b101 )
b101 *
1"
#276000
b100 (
b11101 '
#280000
0"
#285000
b100 !
b100 )
b100 *
1"
#286000
b11 (
b11110 '
#290000
0"
#295000
b11 !
b11 )
b11 *
1"
#296000
b10 (
b11111 '
#300000
0"
#305000
b10 !
b10 )
b10 *
1"
#306000
b1 (
b100000 '
#310000
0"
#315000
b1 !
b1 )
b1 *
1"
#316000
b0 (
b100001 '
#320000
0"
#325000
b0 !
b0 )
b0 *
1"
#326000
b11111111111111111111111111111111 (
b100010 '
